Workbook

Sheet Read Me
A1: How to read this workbook
A3: Summary | B3: Key numbers next to the MT5 report's own figures, verdicts, findings, balance and drawdown charts.
A4: Yearly / Monthly / Weekly / Daily | B4: One row per period: trades, wins, win rate, net, profit factor, best/worst trade, total R, start/end balance and return. Daily flags days that hit the daily loss limit.
A5: Calendar | B5: Year x month grid of net profit (colour scale), trades per month and win rate per month.
A6: Trades | B6: Every trade on one row: entry deal matched to its exit, SL/TP, planned risk, exit reason, R, hold time, balance and drawdown. Use the filter arrows in the header row.
A7: Breakdown | B7: Results split by side, setup, exit reason, weekday, entry hour, hold time, SL size, year, and the R distribution.
A8: Drawdowns & Streaks | B8: The 10 deepest drawdown periods with dates and recovery time, longest win/loss streaks.
A9: MT5 Report / Settings | B9: The tester's original statistics and the EA inputs used.
A11: Dates | B11: Profit is booked on the trade's CLOSE date/time (broker server time).
A12: R multiple | B12: Net profit / planned risk. Planned risk = SL distance x lots x $ per point per lot (Summary C6).
A13: Win / Loss | B13: Breakeven stops that close a few dollars negative (slippage/commission) count as losses, as in MT5.
A14: Colours | B14: Blue = data from the MT5 report or inputs you may change. Black = formulas. Yellow = inputs.
A15: Source | B15: MT5 Strategy Tester report: Pdh pdl m1 atr on NDX100.m_S0, 883 trades. Net profit here matches the report's Total Net Profit (17717.69).

Sheet Summary
B1: Backtest analysis
B2: Pdh pdl m1 atr | NDX100.m_S0 | M1 (2023.04.01 - 2026.10.01) | 100% real ticks
B3: Blue cells are inputs: change them and every sheet recalculates.
B5: Starting balance | C5: 100000 | F5: From the report (Initial Deposit).
B6: $ per 1.00 point per 1.00 lot | C6: 20 | F6: Measured from the trades (profit / points / lots, median). NDX100.m_S0: 1 lot moving 1 point = $20.
B7: Daily loss limit (prop rule) | C7: 0.025 | F7: Used for the breach checks on Daily. Matches the EA input DailyLossPct when present.
B8: Max drawdown limit (prop rule) | C8: 0.1 | F8: Typical prop-firm overall limit.
B10: Metric | C10: Value | D10: MT5 report | E10: Verdict | F10: What it means
B11: RESULT
B12: Net profit | C12: =SUM(Trades!$X$2:$X$884) -> 17717.69 | D12: 17717.69 | E12: =IF(C12>0,"Profitable","Losing") -> Profitable | F12: Total money made over the whole test, after commission and swap.
B13: Final balance | C13: =C5+C12 -> 117717.69
B14: Return on starting balance | C14: =IFERROR(C12/C5,0) -> 0.1771769
B15: Gross profit | C15: =SUMIF(Trades!$X$2:$X$884,">0") -> 64334.51 | D15: 64334.51 | F15: Sum of all winning trades.
B16: Gross loss | C16: =SUMIF(Trades!$X$2:$X$884,"<0") -> -46616.82 | D16: -46616.82 | F16: Sum of all losing trades.
B17: Profit factor | C17: =IFERROR(C15/-C16,0) -> 1.3800708 | D17: 1.380071 | E17: =IF(C17>=1.5,"Strong",IF(C17>=1.2,"Good",IF(C17>=1,"Weak","Losing"))) -> Good | F17: Gross profit / gross loss. 1.2+ is decent for an intraday system, 1.5+ strong.
B18: Expectancy per trade $ | C18: =IFERROR(C12/C20,0) -> 20.065334 | D18: 20.065334 | F18: What one trade earns on average.
B19: TRADES
B20: Total trades | C20: =COUNT(Trades!$X$2:$X$884) -> 883 | D20: 883
B21: Wins | C21: =COUNTIF(Trades!$Z$2:$Z$884,"Win") -> 282 | D21: 290 (32.84%)
B22: Losses | C22: =COUNTIF(Trades!$Z$2:$Z$884,"Loss") -> 593 | D22: 593 (67.16%) | F22: Includes breakeven stops that lost a little to slippage.
B23: Win rate | C23: =IFERROR(C21/C20,0) -> 0.3193658
B24: Average win | C24: =IFERROR(AVERAGEIF(Trades!$X$2:$X$884,">0"),0) -> 228.13656 | D24: 221.84314
B25: Average loss | C25: =IFERROR(AVERAGEIF(Trades!$X$2:$X$884,"<0"),0) -> -78.611838 | D25: -78.611838
B26: Win/loss size ratio | C26: =IFERROR(C24/-C25,0) -> 2.9020637 | F26: Average win / average loss.
B27: Break-even win rate needed | C27: =IFERROR(-C25/(C24-C25),0) -> 0.25627465 | E27: =IF(C23>C27,"Above break-even","Below break-even") -> Above break-even | F27: Win rate needed to break even with these win/loss sizes.
B28: Largest win | C28: =MAX(Trades!$X$2:$X$884) -> 1033.59 | D28: 1033.59
B29: Largest loss | C29: =MIN(Trades!$X$2:$X$884) -> -568.08 | D29: -568.08
B30: Long trades / net | C30: =COUNTIF(Trades!$J$2:$J$884,"BUY") -> 508 | D30: 508 (35.24%) | E30: =SUMIF(Trades!$J$2:$J$884,"BUY",Trades!$X$2:$X$884) -> 9002.57 | F30: Verdict column = net $ of longs.
B31: Short trades / net | C31: =COUNTIF(Trades!$J$2:$J$884,"SELL") -> 375 | D31: 375 (29.60%) | E31: =SUMIF(Trades!$J$2:$J$884,"SELL",Trades!$X$2:$X$884) -> 8715.12 | F31: Verdict column = net $ of shorts.
B32: RISK (R multiples)
B33: Average planned risk per trade $ | C33: =AVERAGE(Trades!$R$2:$R$884) -> 114.90994 | F33: SL distance x lots x $ per point.
B34: Average planned risk % of balance | C34: =IFERROR(AVERAGE(Trades!$R$2:$R$884)/AVERAGE(Trades!$AD$2:$AD$884),0) -> 0.0010574461 | F34: Compare with the EA's RiskPercent.
B35: Average SL distance (points) | C35: =AVERAGE(Trades!$P$2:$P$884) -> 25.906376
B36: Average R per trade | C36: =AVERAGE(Trades!$Y$2:$Y$884) -> 0.20007864 | E36: =IF(C36>0,"Positive edge","No edge") -> Positive edge | F36: Expectancy in units of risk.
B37: Total R | C37: =SUM(Trades!$Y$2:$Y$884) -> 176.66944
B38: Average R of full stop losses | C38: =IFERROR(AVERAGEIF(Trades!$T$2:$T$884,"Initial stop loss",Trades!$Y$2:$Y$884),0) -> -1.0260953 | E38: =IF(C38<-1.05,"Losses overshoot","OK") -> OK | F38: -1.00R = lost exactly the plan. Below -1.05R = slippage.
B39: Average R of take profits | C39: =IFERROR(AVERAGEIF(Trades!$T$2:$T$884,"Take profit",Trades!$Y$2:$Y$884),0) -> 2.0545413
B40: DRAWDOWN & PROP RULES
B41: Max closed-trade drawdown $ | C41: =MAX(Trades!$AF$2:$AF$884) -> 2246.72 | D41: 2 246.72 (1.92%) | F41: Peak-to-low of the balance.
B42: Max closed-trade drawdown % | C42: =MAX(Trades!$AG$2:$AG$884) -> 0.019223595 | D42: 2 470.08 (2.11%) | E42: =IF(C42<=C8/2,"Safe",IF(C42<=C8,"Close to limit","Breach")) -> Safe | F42: MT5 report column shows the equity drawdown (includes open trades).
B43: Worst day $ | C43: =MIN(Daily!F2:F777) -> -863.72 | F43: See Daily sheet.
B44: Worst day % of start balance | C44: =MIN(Daily!N2:N777) -> -0.0073906425 | E44: =IF(-C44>=C7,"Breach","OK") -> OK | F44: Compared with the daily loss limit.
B45: Days breaching daily loss limit | C45: =COUNTIF(Daily!O2:O777,"BREACH") -> 0
B46: Worst week $ | C46: =MIN(Weekly!F2:F183) -> -1014.69
B47: Worst month $ | C47: =MIN(Monthly!F2:F43) -> -746.08
B48: Recovery factor | C48: =IFERROR(C12/C41,0) -> 7.886025 | D48: 7.172922 | F48: Net profit / max drawdown. 3+ is good.
B49: CONSISTENCY
B50: Trading days | C50: =COUNT(Daily!A2:A777) -> 776 | F50: Days with at least one closed trade.
B51: Green days % | C51: =IFERROR(COUNTIF(Daily!F2:F777,">0")/C50,0) -> 0.34149485
B52: Average day $ | C52: =IFERROR(C12/C50,0) -> 22.832075
B53: Months profitable | C53: =COUNTIF(Monthly!F2:F43,">0")&" of "&COUNT(Monthly!F2:F43) -> 28 of 42
B54: Average month $ | C54: =AVERAGE(Monthly!F2:F43) -> 421.84976
B55: Best day share of total profit | C55: =IFERROR(MAX(Daily!F2:F777)/C12,0) -> 0.05821865 | E55: =IF(C55>0.3,"Too concentrated","OK") -> OK | F55: Prop consistency rules often require the best day < 30-50% of total profit.
B56: Median hold (minutes) | C56: =MEDIAN(Trades!$AA$2:$AA$884) -> 11.3 | D56: 0:38:54 | F56: MT5 column = average.
B57: Sharpe ratio (MT5) | D57: 10.95045 | F57: As reported by MT5.
B58: Z-score (MT5) | D58: 1.91 (94.39%) | F58: Near +/-2 = wins/losses cluster in streaks; near 0 = random order.
B60: FINDINGS (computed from this report)
B61: 1. Result: 883 trades, net $17,718 (17.7% on $100,000), profit factor 1.38, win rate 31.9%, average +0.200R per trade.
B62: 2. Exits: Initial stop loss 386 (44%), net $-45,673 | Take profit 282 (32%), net $64,335 | Breakeven stop 215 (24%), net $-944.
B63: 3. Breakeven stops: 215 trades (24%) reached +1R then came back to entry; together they cost $944 (exit slippage, swap, commission). They are counted as losses by MT5, which is why the win rate looks low while the system is profitable.
B64: 4. Full stop losses average -1.03R (worst -1.46R). Take profits average 2.05R.
B65: 5. 776 trading days, 34% of them green; worst day 2026-03-23 $-864; 28 of 42 months profitable; best month 2025-04 ($2,502), worst 2025-12 ($-746).
B66: 6. Deepest closed-trade drawdown $2,247 (1.92% of the peak), from 2026-03-19 to the low on 2026-04-13, recovered 2026-09-01. Prop limits used here: daily 2.5%, max 10% - far away.
B67: 7. Longs $9,003 vs shorts $8,715. Best entry hours (server): 01:00 $10,454, 16:00 $1,989, 12:00 $785; worst: 02:00 $-834, 17:00 $-374, 15:00 $-137.
B68: 8. Median hold 11 min, 23 trades closed within 1 minute (those are mostly decided by noise/spread). Commission total $0.00, swap $-230.01.
B69: 9. Concentration: entries in the 01:00 server hour made $10,454 = 59% of the total profit from 176 trades. All other hours together: 707 trades, net $7,263, profit factor 1.20. Check that this hour is tradable live (session open gaps, spread on this zero-spread test symbol).
B70: 10. Position size: the trades risked 0.11% of balance on average (SL distance x lots x $20), while RiskPercent = 0.5%. The EA sizes positions much smaller than the setting - check its tick value / lot step / margin cap on this symbol; returns and drawdowns scale with it.

Sheet Yearly
A1: Year | B1: Trades | C1: Wins | D1: Losses | E1: Win rate | F1: Net profit | G1: Gross profit | H1: Gross loss | I1: Profit factor | J1: Best trade | K1: Worst trade | L1: Total R | M1: Start balance | N1: Return % | O1: Limit check | P1: End balance | Q1: Cumulative net
A2: 2023 | B2: =COUNTIFS(Trades!$G$2:$G$884,$A2) -> 194 | C2: =COUNTIFS(Trades!$G$2:$G$884,$A2,Trades!$Z$2:$Z$884,"Win") -> 65 | D2: =COUNTIFS(Trades!$G$2:$G$884,$A2,Trades!$Z$2:$Z$884,"Loss") -> 129 | E2: =IFERROR(C2/B2,0) -> 0.33505155 | F2: =SUMIFS(Trades!$X$2:$X$884,Trades!$G$2:$G$884,$A2) -> 4466.65 | G2: =SUMIFS(Trades!$X$2:$X$884,Trades!$G$2:$G$884,$A2,Trades!$X$2:$X$884,">0") -> 12898.01 | H2: =SUMIFS(Trades!$X$2:$X$884,Trades!$G$2:$G$884,$A2,Trades!$X$2:$X$884,"<0") -> -8431.36 | I2: =IFERROR(G2/-H2,"no loss") -> 1.5297663 | J2: =_xlfn.MAXIFS(Trades!$X$2:$X$884,Trades!$G$2:$G$884,$A2) -> 637.98 | K2: =_xlfn.MINIFS(Trades!$X$2:$X$884,Trades!$G$2:$G$884,$A2) -> -420.99 | L2: =SUMIFS(Trades!$Y$2:$Y$884,Trades!$G$2:$G$884,$A2) -> 39.248908 | M2: =Summary!$C$5 -> 100000 | N2: =IFERROR(F2/M2,0) -> 0.0446665 | O2: =IF(F2>0,"up","down") -> up | P2: =M2+F2 -> 104466.65 | Q2: =P2-Summary!$C$5 -> 4466.65
A3: 2024 | B3: =COUNTIFS(Trades!$G$2:$G$884,$A3) -> 244 | C3: =COUNTIFS(Trades!$G$2:$G$884,$A3,Trades!$Z$2:$Z$884,"Win") -> 73 | D3: =COUNTIFS(Trades!$G$2:$G$884,$A3,Trades!$Z$2:$Z$884,"Loss") -> 167 | E3: =IFERROR(C3/B3,0) -> 0.29918033 | F3: =SUMIFS(Trades!$X$2:$X$884,Trades!$G$2:$G$884,$A3) -> 2375.02 | G3: =SUMIFS(Trades!$X$2:$X$884,Trades!$G$2:$G$884,$A3,Trades!$X$2:$X$884,">0") -> 13635.8 | H3: =SUMIFS(Trades!$X$2:$X$884,Trades!$G$2:$G$884,$A3,Trades!$X$2:$X$884,"<0") -> -11260.78 | I3: =IFERROR(G3/-H3,"no loss") -> 1.2109108 | J3: =_xlfn.MAXIFS(Trades!$X$2:$X$884,Trades!$G$2:$G$884,$A3) -> 556.6 | K3: =_xlfn.MINIFS(Trades!$X$2:$X$884,Trades!$G$2:$G$884,$A3) -> -455.88 | L3: =SUMIFS(Trades!$Y$2:$Y$884,Trades!$G$2:$G$884,$A3) -> 42.423085 | M3: =P2 -> 104466.65 | N3: =IFERROR(F3/M3,0) -> 0.02273472 | O3: =IF(F3>0,"up","down") -> up | P3: =M3+F3 -> 106841.67 | Q3: =P3-Summary!$C$5 -> 6841.67
A4: 2025 | B4: =COUNTIFS(Trades!$G$2:$G$884,$A4) -> 257 | C4: =COUNTIFS(Trades!$G$2:$G$884,$A4,Trades!$Z$2:$Z$884,"Win") -> 84 | D4: =COUNTIFS(Trades!$G$2:$G$884,$A4,Trades!$Z$2:$Z$884,"Loss") -> 170 | E4: =IFERROR(C4/B4,0) -> 0.32684825 | F4: =SUMIFS(Trades!$X$2:$X$884,Trades!$G$2:$G$884,$A4) -> 7225.36 | G4: =SUMIFS(Trades!$X$2:$X$884,Trades!$G$2:$G$884,$A4,Trades!$X$2:$X$884,">0") -> 22275.79 | H4: =SUMIFS(Trades!$X$2:$X$884,Trades!$G$2:$G$884,$A4,Trades!$X$2:$X$884,"<0") -> -15050.43 | I4: =IFERROR(G4/-H4,"no loss") -> 1.4800766 | J4: =_xlfn.MAXIFS(Trades!$X$2:$X$884,Trades!$G$2:$G$884,$A4) -> 1033.59 | K4: =_xlfn.MINIFS(Trades!$X$2:$X$884,Trades!$G$2:$G$884,$A4) -> -537.23 | L4: =SUMIFS(Trades!$Y$2:$Y$884,Trades!$G$2:$G$884,$A4) -> 52.738723 | M4: =P3 -> 106841.67 | N4: =IFERROR(F4/M4,0) -> 0.067626798 | O4: =IF(F4>0,"up","down") -> up | P4: =M4+F4 -> 114067.03 | Q4: =P4-Summary!$C$5 -> 14067.03
A5: 2026 | B5: =COUNTIFS(Trades!$G$2:$G$884,$A5) -> 188 | C5: =COUNTIFS(Trades!$G$2:$G$884,$A5,Trades!$Z$2:$Z$884,"Win") -> 60 | D5: =COUNTIFS(Trades!$G$2:$G$884,$A5,Trades!$Z$2:$Z$884,"Loss") -> 127 | E5: =IFERROR(C5/B5,0) -> 0.31914894 | F5: =SUMIFS(Trades!$X$2:$X$884,Trades!$G$2:$G$884,$A5) -> 3650.66 | G5: =SUMIFS(Trades!$X$2:$X$884,Trades!$G$2:$G$884,$A5,Trades!$X$2:$X$884,">0") -> 15524.91 | H5: =SUMIFS(Trades!$X$2:$X$884,Trades!$G$2:$G$884,$A5,Trades!$X$2:$X$884,"<0") -> -11874.25 | I5: =IFERROR(G5/-H5,"no loss") -> 1.3074434 | J5: =_xlfn.MAXIFS(Trades!$X$2:$X$884,Trades!$G$2:$G$884,$A5) -> 721.31 | K5: =_xlfn.MINIFS(Trades!$X$2:$X$884,Trades!$G$2:$G$884,$A5) -> -568.08 | L5: =SUMIFS(Trades!$Y$2:$Y$884,Trades!$G$2:$G$884,$A5) -> 42.258728 | M5: =P4 -> 114067.03 | N5: =IFERROR(F5/M5,0) -> 0.032004515 | O5: =IF(F5>0,"up","down") -> up | P5: =M5+F5 -> 117717.69 | Q5: =P5-Summary!$C$5 -> 17717.69
A7: TOTAL | B7: =SUM(B2:B5) -> 883 | C7: =SUM(C2:C5) -> 282 | D7: =SUM(D2:D5) -> 593 | E7: =IFERROR(C7/B7,0) -> 0.3193658 | F7: =SUM(F2:F5) -> 17717.69 | G7: =SUM(G2:G5) -> 64334.51 | H7: =SUM(H2:H5) -> -46616.82 | I7: =IFERROR(G7/-H7,0) -> 1.3800708 | L7: =SUM(L2:L5) -> 176.66944 | N7: =IFERROR(F7/M2,0) -> 0.1771769 | O7: =COUNTIF(F2:F5,">0")&" up / "&COUNTIF(F2:F5,"<0")&" down" -> 4 up / 0 down
A8: Partial years: the test period decides the first and last year's length.

Sheet Monthly
A1: Month | B1: Trades | C1: Wins | D1: Losses | E1: Win rate | F1: Net profit | G1: Gross profit | H1: Gross loss | I1: Profit factor | J1: Best trade | K1: Worst trade | L1: Total R | M1: Start balance | N1: Return % | O1: Limit check | P1: End balance | Q1: Cumulative net
A2: 2023-04 | B2: =COUNTIFS(Trades!$F$2:$F$884,$A2) -> 18 | C2: =COUNTIFS(Trades!$F$2:$F$884,$A2,Trades!$Z$2:$Z$884,"Win") -> 5 | D2: =COUNTIFS(Trades!$F$2:$F$884,$A2,Trades!$Z$2:$Z$884,"Loss") -> 13 | E2: =IFERROR(C2/B2,0) -> 0.27777778 | F2: =SUMIFS(Trades!$X$2:$X$884,Trades!$F$2:$F$884,$A2) -> -638.22 | G2: =SUMIFS(Trades!$X$2:$X$884,Trades!$F$2:$F$884,$A2,Trades!$X$2:$X$884,">0") -> 580.99 | H2: =SUMIFS(Trades!$X$2:$X$884,Trades!$F$2:$F$884,$A2,Trades!$X$2:$X$884,"<0") -> -1219.21 | I2: =IFERROR(G2/-H2,"no loss") -> 0.47652988 | J2: =_xlfn.MAXIFS(Trades!$X$2:$X$884,Trades!$F$2:$F$884,$A2) -> 170.07 | K2: =_xlfn.MINIFS(Trades!$X$2:$X$884,Trades!$F$2:$F$884,$A2) -> -354.48 | L2: =SUMIFS(Trades!$Y$2:$Y$884,Trades!$F$2:$F$884,$A2) -> -1.2776809 | M2: =Summary!$C$5 -> 100000 | N2: =IFERROR(F2/M2,0) -> -0.0063822 | O2: =IF(F2>0,"up","down") -> down | P2: =M2+F2 -> 99361.78 | Q2: =P2-Summary!$C$5 -> -638.22
A3: 2023-05 | B3: =COUNTIFS(Trades!$F$2:$F$884,$A3) -> 25 | C3: =COUNTIFS(Trades!$F$2:$F$884,$A3,Trades!$Z$2:$Z$884,"Win") -> 6 | D3: =COUNTIFS(Trades!$F$2:$F$884,$A3,Trades!$Z$2:$Z$884,"Loss") -> 19 | E3: =IFERROR(C3/B3,0) -> 0.24 | F3: =SUMIFS(Trades!$X$2:$X$884,Trades!$F$2:$F$884,$A3) -> -25.49 | G3: =SUMIFS(Trades!$X$2:$X$884,Trades!$F$2:$F$884,$A3,Trades!$X$2:$X$884,">0") -> 1303.66 | H3: =SUMIFS(Trades!$X$2:$X$884,Trades!$F$2:$F$884,$A3,Trades!$X$2:$X$884,"<0") -> -1329.15 | I3: =IFERROR(G3/-H3,"no loss") -> 0.98082233 | J3: =_xlfn.MAXIFS(Trades!$X$2:$X$884,Trades!$F$2:$F$884,$A3) -> 316.67 | K3: =_xlfn.MINIFS(Trades!$X$2:$X$884,Trades!$F$2:$F$884,$A3) -> -365.06 | L3: =SUMIFS(Trades!$Y$2:$Y$884,Trades!$F$2:$F$884,$A3) -> -2.5043016 | M3: =P2 -> 99361.78 | N3: =IFERROR(F3/M3,0) -> -0.00025653727 | O3: =IF(F3>0,"up","down") -> down | P3: =M3+F3 -> 99336.29 | Q3: =P3-Summary!$C$5 -> -663.71
A4: 2023-06 | B4: =COUNTIFS(Trades!$F$2:$F$884,$A4) -> 21 | C4: =COUNTIFS(Trades!$F$2:$F$884,$A4,Trades!$Z$2:$Z$884,"Win") -> 9 | D4: =COUNTIFS(Trades!$F$2:$F$884,$A4,Trades!$Z$2:$Z$884,"Loss") -> 12 | E4: =IFERROR(C4/B4,0) -> 0.42857143 | F4: =SUMIFS(Trades!$X$2:$X$884,Trades!$F$2:$F$884,$A4) -> 1177.99 | G4: =SUMIFS(Trades!$X$2:$X$884,Trades!$F$2:$F$884,$A4,Trades!$X$2:$X$884,">0") -> 1683.87 | H4: =SUMIFS(Trades!$X$2:$X$884,Trades!$F$2:$F$884,$A4,Trades!$X$2:$X$884,"<0") -> -505.88 | I4: =IFERROR(G4/-H4,"no loss") -> 3.3285957 | J4: =_xlfn.MAXIFS(Trades!$X$2:$X$884,Trades!$F$2:$F$884,$A4) -> 313.44 | K4: =_xlfn.MINIFS(Trades!$X$2:$X$884,Trades!$F$2:$F$884,$A4) -> -133.3 | L4: =SUMIFS(Trades!$Y$2:$Y$884,Trades!$F$2:$F$884,$A4) -> 12.368619 | M4: =P3 -> 99336.29 | N4: =IFERROR(F4/M4,0) -> 0.011858607 | O4: =IF(F4>0,"up","down") -> up | P4: =M4+F4 -> 100514.28 | Q4: =P4-Summary!$C$5 -> 514.28
A5: 2023-07 | B5: =COUNTIFS(Trades!$F$2:$F$884,$A5) -> 22 | C5: =COUNTIFS(Trades!$F$2:$F$884,$A5,Trades!$Z$2:$Z$884,"Win") -> 9 | D5: =COUNTIFS(Trades!$F$2:$F$884,$A5,Trades!$Z$2:$Z$884,"Loss") -> 13 | E5: =IFERROR(C5/B5,0) -> 0.40909091 | F5: =SUMIFS(Trades!$X$2:$X$884,Trades!$F$2:$F$884,$A5) -> 343.27 | G5: =SUMIFS(Trades!$X$2:$X$884,Trades!$F$2:$F$884,$A5,Trades!$X$2:$X$884,">0") -> 1330.06 | H5: =SUMIFS(Trades!$X$2:$X$884,Trades!$F$2:$F$884,$A5,Trades!$X$2:$X$884,"<0") -> -986.79 | I5: =IFERROR(G5/-H5,"no loss") -> 1.3478653 | J5: =_xlfn.MAXIFS(Trades!$X$2:$X$884,Trades!$F$2:$F$884,$A5) -> 310.69 | K5: =_xlfn.MINIFS(Trades!$X$2:$X$884,Trades!$F$2:$F$884,$A5) -> -261.23 | L5: =SUMIFS(Trades!$Y$2:$Y$884,Trades!$F$2:$F$884,$A5) -> 8.1213754 | M5: =P4 -> 100514.28 | N5: =IFERROR(F5/M5,0) -> 0.0034151366 | O5: =IF(F5>0,"up","down") -> up | P5: =M5+F5 -> 100857.55 | Q5: =P5-Summary!$C$5 -> 857.55
A6: 2023-08 | B6: =COUNTIFS(Trades!$F$2:$F$884,$A6) -> 25 | C6: =COUNTIFS(Trades!$F$2:$F$884,$A6,Trades!$Z$2:$Z$884,"Win") -> 9 | D6: =COUNTIFS(Trades!$F$2:$F$884,$A6,Trades!$Z$2:$Z$884,"Loss") -> 16 | E6: =IFERROR(C6/B6,0) -> 0.36 | F6: =SUMIFS(Trades!$X$2:$X$884,Trades!$F$2:$F$884,$A6) -> 883.52 | G6: =SUMIFS(Trades!$X$2:$X$884,Trades!$F$2:$F$884,$A6,Trades!$X$2:$X$884,">0") -> 2004.07 | H6: =SUMIFS(Trades!$X$2:$X$884,Trades!$F$2:$F$884,$A6,Trades!$X$2:$X$884,"<0") -> -1120.55 | I6: =IFERROR(G6/-H6,"no loss") -> 1.7884699 | J6: =_xlfn.MAXIFS(Trades!$X$2:$X$884,Trades!$F$2:$F$884,$A6) -> 422.82 | K6: =_xlfn.MINIFS(Trades!$X$2:$X$884,Trades!$F$2:$F$884,$A6) -> -193.14 | L6: =SUMIFS(Trades!$Y$2:$Y$884,Trades!$F$2:$F$884,$A6) -> 4.4747419 | M6: =P5 -> 100857.55 | N6: =IFERROR(F6/M6,0) -> 0.008760078 | O6: =IF(F6>0,"up","down") -> up | P6: =M6+F6 -> 101741.07 | Q6: =P6-Summary!$C$5 -> 1741.07
A7: 2023-09 | B7: =COUNTIFS(Trades!$F$2:$F$884,$A7) -> 21 | C7: =COUNTIFS(Trades!$F$2:$F$884,$A7,Trades!$Z$2:$Z$884,"Win") -> 7 | D7: =COUNTIFS(Trades!$F$2:$F$884,$A7,Trades!$Z$2:$Z$884,"Loss") -> 14 | E7: =IFERROR(C7/B7,0) -> 0.33333333 | F7: =SUMIFS(Trades!$X$2:$X$884,Trades!$F$2:$F$884,$A7) -> 1438.95 | G7: =SUMIFS(Trades!$X$2:$X$884,Trades!$F$2:$F$884,$A7,Trades!$X$2:$X$884,">0") -> 1932.3 | H7: =SUMIFS(Trades!$X$2:$X$884,Trades!$F$2:$F$884,$A7,Trades!$X$2:$X$884,"<0") -> -493.35 | I7: =IFERROR(G7/-H7,"no loss") -> 3.916692 | J7: =_xlfn.MAXIFS(Trades!$X$2:$X$884,Trades!$F$2:$F$884,$A7) -> 385.35 | K7: =_xlfn.MINIFS(Trades!$X$2:$X$884,Trades!$F$2:$F$884,$A7) -> -109.55 | L7: =SUMIFS(Trades!$Y$2:$Y$884,Trades!$F$2:$F$884,$A7) -> 4.7409601 | M7: =P6 -> 101741.07 | N7: =IFERROR(F7/M7,0) -> 0.014143256 | O7: =IF(F7>0,"up","down") -> up | P7: =M7+F7 -> 103180.02 | Q7: =P7-Summary!$C$5 -> 3180.02
A8: 2023-10 | B8: =COUNTIFS(Trades!$F$2:$F$884,$A8) -> 21 | C8: =COUNTIFS(Trades!$F$2:$F$884,$A8,Trades!$Z$2:$Z$884,"Win") -> 8 | D8: =COUNTIFS(Trades!$F$2:$F$884,$A8,Trades!$Z$2:$Z$884,"Loss") -> 13 | E8: =IFERROR(C8/B8,0) -> 0.38095238 | F8: =SUMIFS(Trades!$X$2:$X$884,Trades!$F$2:$F$884,$A8) -> 990.48 | G8: =SUMIFS(Trades!$X$2:$X$884,Trades!$F$2:$F$884,$A8,Trades!$X$2:$X$884,">0") -> 2292.81 | H8: =SUMIFS(Trades!$X$2:$X$884,Trades!$F$2:$F$884,$A8,Trades!$X$2:$X$884,"<0") -> -1302.33 | I8: =IFERROR(G8/-H8,"no loss") -> 1.7605446 | J8: =_xlfn.MAXIFS(Trades!$X$2:$X$884,Trades!$F$2:$F$884,$A8) -> 637.98 | K8: =_xlfn.MINIFS(Trades!$X$2:$X$884,Trades!$F$2:$F$884,$A8) -> -420.99 | L8: =SUMIFS(Trades!$Y$2:$Y$884,Trades!$F$2:$F$884,$A8) -> 8.2395132 | M8: =P7 -> 103180.02 | N8: =IFERROR(F8/M8,0) -> 0.0095995329 | O8: =IF(F8>0,"up","down") -> up | P8: =M8+F8 -> 104170.5 | Q8: =P8-Summary!$C$5 -> 4170.5
A9: 2023-11 | B9: =COUNTIFS(Trades!$F$2:$F$884,$A9) -> 22 | C9: =COUNTIFS(Trades!$F$2:$F$884,$A9,Trades!$Z$2:$Z$884,"Win") -> 8 | D9: =COUNTIFS(Trades!$F$2:$F$884,$A9,Trades!$Z$2:$Z$884,"Loss") -> 14 | E9: =IFERROR(C9/B9,0) -> 0.36363636 | F9: =SUMIFS(Trades!$X$2:$X$884,Trades!$F$2:$F$884,$A9) -> 724.77 | G9: =SUMIFS(Trades!$X$2:$X$884,Trades!$F$2:$F$884,$A9,Trades!$X$2:$X$884,">0") -> 1360.22 | H9: =SUMIFS(Trades!$X$2:$X$884,Trades!$F$2:$F$884,$A9,Trades!$X$2:$X$884,"<0") -> -635.45 | I9: =IFERROR(G9/-H9,"no loss") -> 2.1405618 | J9: =_xlfn.MAXIFS(Trades!$X$2:$X$884,Trades!$F$2:$F$884,$A9) -> 373.64 | K9: =_xlfn.MINIFS(Trades!$X$2:$X$884,Trades!$F$2:$F$884,$A9) -> -158.21 | L9: =SUMIFS(Trades!$Y$2:$Y$884,Trades!$F$2:$F$884,$A9) -> 8.0303055 | M9: =P8 -> 104170.5 | N9: =IFERROR(F9/M9,0) -> 0.006957536 | O9: =IF(F9>0,"up","down") -> up | P9: =M9+F9 -> 104895.27 | Q9: =P9-Summary!$C$5 -> 4895.27
A10: 2023-12 | B10: =COUNTIFS(Trades!$F$2:$F$884,$A10) -> 19 | C10: =COUNTIFS(Trades!$F$2:$F$884,$A10,Trades!$Z$2:$Z$884,"Win") -> 4 | D10: =COUNTIFS(Trades!$F$2:$F$884,$A10,Trades!$Z$2:$Z$884,"Loss") -> 15 | E10: =IFERROR(C10/B10,0) -> 0.21052632 | F10: =SUMIFS(Trades!$X$2:$X$884,Trades!$F$2:$F$884,$A10) -> -428.62 | G10: =SUMIFS(Trades!$X$2:$X$884,Trades!$F$2:$F$884,$A10,Trades!$X$2:$X$884,">0") -> 410.03 | H10: =SUMIFS(Trades!$X$2:$X$884,Trades!$F$2:$F$884,$A10,Trades!$X$2:$X$884,"<0") -> -838.65 | I10: =IFERROR(G10/-H10,"no loss") -> 0.48891671 | J10: =_xlfn.MAXIFS(Trades!$X$2:$X$884,Trades!$F$2:$F$884,$A10) -> 279.72 | K10: =_xlfn.MINIFS(Trades!$X$2:$X$884,Trades!$F$2:$F$884,$A10) -> -162.57 | L10: =SUMIFS(Trades!$Y$2:$Y$884,Trades!$F$2:$F$884,$A10) -> -2.9446249 | M10: =P9 -> 104895.27 | N10: =IFERROR(F10/M10,0) -> -0.0040861709 | O10: =IF(F10>0,"up","down") -> down | P10: =M10+F10 -> 104466.65 | Q10: =P10-Summary!$C$5 -> 4466.65
A11: 2024-01 | B11: =COUNTIFS(Trades!$F$2:$F$884,$A11) -> 22 | C11: =COUNTIFS(Trades!$F$2:$F$884,$A11,Trades!$Z$2:$Z$884,"Win") -> 10 | D11: =COUNTIFS(Trades!$F$2:$F$884,$A11,Trades!$Z$2:$Z$884,"Loss") -> 12 | E11: =IFERROR(C11/B11,0) -> 0.45454545 | F11: =SUMIFS(Trades!$X$2:$X$884,Trades!$F$2:$F$884,$A11) -> 1010.77 | G11: =SUMIFS(Trades!$X$2:$X$884,Trades!$F$2:$F$884,$A11,Trades!$X$2:$X$884,">0") -> 1656.1 | H11: =SUMIFS(Trades!$X$2:$X$884,Trades!$F$2:$F$884,$A11,Trades!$X$2:$X$884,"<0") -> -645.33 | I11: =IFERROR(G11/-H11,"no loss") -> 2.5662839 | J11: =_xlfn.MAXIFS(Trades!$X$2:$X$884,Trades!$F$2:$F$884,$A11) -> 525.69 | K11: =_xlfn.MINIFS(Trades!$X$2:$X$884,Trades!$F$2:$F$884,$A11) -> -140.13 | L11: =SUMIFS(Trades!$Y$2:$Y$884,Trades!$F$2:$F$884,$A11) -> 11.090573 | M11: =P10 -> 104466.65 | N11: =IFERROR(F11/M11,0) -> 0.009675528 | O11: =IF(F11>0,"up","down") -> up | P11: =M11+F11 -> 105477.42 | Q11: =P11-Summary!$C$5 -> 5477.42
A12: 2024-02 | B12: =COUNTIFS(Trades!$F$2:$F$884,$A12) -> 19 | C12: =COUNTIFS(Trades!$F$2:$F$884,$A12,Trades!$Z$2:$Z$884,"Win") -> 5 | D12: =COUNTIFS(Trades!$F$2:$F$884,$A12,Trades!$Z$2:$Z$884,"Loss") -> 14 | E12: =IFERROR(C12/B12,0) -> 0.26315789 | F12: =SUMIFS(Trades!$X$2:$X$884,Trades!$F$2:$F$884,$A12) -> 1018.44 | G12: =SUMIFS(Trades!$X$2:$X$884,Trades!$F$2:$F$884,$A12,Trades!$X$2:$X$884,">0") -> 1443.47 | H12: =SUMIFS(Trades!$X$2:$X$884,Trades!$F$2:$F$884,$A12,Trades!$X$2:$X$884,"<0") -> -425.03 | I12: =IFERROR(G12/-H12,"no loss") -> 3.3961603 | J12: =_xlfn.MAXIFS(Trades!$X$2:$X$884,Trades!$F$2:$F$884,$A12) -> 498.73 | K12: =_xlfn.MINIFS(Trades!$X$2:$X$884,Trades!$F$2:$F$884,$A12) -> -130.57 | L12: =SUMIFS(Trades!$Y$2:$Y$884,Trades!$F$2:$F$884,$A12) -> 2.6344646 | M12: =P11 -> 105477.42 | N12: =IFERROR(F12/M12,0) -> 0.0096555263 | O12: =IF(F12>0,"up","down") -> up | P12: =M12+F12 -> 106495.86 | Q12: =P12-Summary!$C$5 -> 6495.86
A13: 2024-03 | B13: =COUNTIFS(Trades!$F$2:$F$884,$A13) -> 19 | C13: =COUNTIFS(Trades!$F$2:$F$884,$A13,Trades!$Z$2:$Z$884,"Win") -> 5 | D13: =COUNTIFS(Trades!$F$2:$F$884,$A13,Trades!$Z$2:$Z$884,"Loss") -> 14 | E13: =IFERROR(C13/B13,0) -> 0.26315789 | F13: =SUMIFS(Trades!$X$2:$X$884,Trades!$F$2:$F$884,$A13) -> -618.59 | G13: =SUMIFS(Trades!$X$2:$X$884,Trades!$F$2:$F$884,$A13,Trades!$X$2:$X$884,">0") -> 450.89 | H13: =SUMIFS(Trades!$X$2:$X$884,Trades!$F$2:$F$884,$A13,Trades!$X$2:$X$884,"<0") -> -1069.48 | I13: =IFERROR(G13/-H13,"no loss") -> 0.42159741 | J13: =_xlfn.MAXIFS(Trades!$X$2:$X$884,Trades!$F$2:$F$884,$A13) -> 126.46 | K13: =_xlfn.MINIFS(Trades!$X$2:$X$884,Trades!$F$2:$F$884,$A13) -> -242.48 | L13: =SUMIFS(Trades!$Y$2:$Y$884,Trades!$F$2:$F$884,$A13) -> 0.77355524 | M13: =P12 -> 106495.86 | N13: =IFERROR(F13/M13,0) -> -0.0058085826 | O13: =IF(F13>0,"up","down") -> down | P13: =M13+F13 -> 105877.27 | Q13: =P13-Summary!$C$5 -> 5877.27
A14: 2024-04 | B14: =COUNTIFS(Trades!$F$2:$F$884,$A14) -> 23 | C14: =COUNTIFS(Trades!$F$2:$F$884,$A14,Trades!$Z$2:$Z$884,"Win") -> 5 | D14: =COUNTIFS(Trades!$F$2:$F$884,$A14,Trades!$Z$2:$Z$884,"Loss") -> 18 | E14: =IFERROR(C14/B14,0) -> 0.2173913 | F14: =SUMIFS(Trades!$X$2:$X$884,Trades!$F$2:$F$884,$A14) -> -540.62 | G14: =SUMIFS(Trades!$X$2:$X$884,Trades!$F$2:$F$884,$A14,Trades!$X$2:$X$884,">0") -> 1375.82 | H14: =SUMIFS(Trades!$X$2:$X$884,Trades!$F$2:$F$884,$A14,Trades!$X$2:$X$884,"<0") -> -1916.44 | I14: =IFERROR(G14/-H14,"no loss") -> 0.71790403 | J14: =_xlfn.MAXIFS(Trades!$X$2:$X$884,Trades!$F$2:$F$884,$A14) -> 405.39 | K14: =_xlfn.MINIFS(Trades!$X$2:$X$884,Trades!$F$2:$F$884,$A14) -> -455.88 | L14: =SUMIFS(Trades!$Y$2:$Y$884,Trades!$F$2:$F$884,$A14) -> -2.2145602 | M14: =P13 -> 105877.27 | N14: =IFERROR(F14/M14,0) -> -0.0051061007 | O14: =IF(F14>0,"up","down") -> down | P14: =M14+F14 -> 105336.65 | Q14: =P14-Summary!$C$5 -> 5336.65
... A43: 2026-09 | B43: =COUNTIFS(Trades!$F$2:$F$884,$A43) -> 20 | C43: =COUNTIFS(Trades!$F$2:$F$884,$A43,Trades!$Z$2:$Z$884,"Win") -> 9 | D43: =COUNTIFS(Trades!$F$2:$F$884,$A43,Trades!$Z$2:$Z$884,"Loss") -> 10 | E43: =IFERROR(C43/B43,0) -> 0.45 | F43: =SUMIFS(Trades!$X$2:$X$884,Trades!$F$2:$F$884,$A43) -> 1106.43 | G43: =SUMIFS(Trades!$X$2:$X$884,Trades!$F$2:$F$884,$A43,Trades!$X$2:$X$884,">0") -> 1517.85 | H43: =SUMIFS(Trades!$X$2:$X$884,Trades!$F$2:$F$884,$A43,Trades!$X$2:$X$884,"<0") -> -411.42 | I43: =IFERROR(G43/-H43,"no loss") -> 3.6892956 | J43: =_xlfn.MAXIFS(Trades!$X$2:$X$884,Trades!$F$2:$F$884,$A43) -> 720.14 | K43: =_xlfn.MINIFS(Trades!$X$2:$X$884,Trades!$F$2:$F$884,$A43) -> -180.88 | L43: =SUMIFS(Trades!$Y$2:$Y$884,Trades!$F$2:$F$884,$A43) -> 13.037907 | M43: =P42 -> 116611.26 | N43: =IFERROR(F43/M43,0) -> 0.0094881918 | O43: =IF(F43>0,"up","down") -> up | P43: =M43+F43 -> 117717.69 | Q43: =P43-Summary!$C$5 -> 17717.69
A45: TOTAL | B45: =SUM(B2:B43) -> 883 | C45: =SUM(C2:C43) -> 282 | D45: =SUM(D2:D43) -> 593 | E45: =IFERROR(C45/B45,0) -> 0.3193658 | F45: =SUM(F2:F43) -> 17717.69 | G45: =SUM(G2:G43) -> 64334.51 | H45: =SUM(H2:H43) -> -46616.82 | I45: =IFERROR(G45/-H45,0) -> 1.3800708 | L45: =SUM(L2:L43) -> 176.66944 | N45: =IFERROR(F45/M2,0) -> 0.1771769 | O45: =COUNTIF(F2:F43,">0")&" up / "&COUNTIF(F2:F43,"<0")&" down" -> 28 up / 14 down

Sheet Calendar
A1: Net profit by month ($) - green = profit, red = loss
A3: Year | B3: Jan | C3: Feb | D3: Mar | E3: Apr | F3: May | G3: Jun | H3: Jul | I3: Aug | J3: Sep | K3: Oct | L3: Nov | M3: Dec | N3: Year total | O3: Return %
A4: 2023 | B4: =SUMIFS(Trades!$X$2:$X$884,Trades!$F$2:$F$884,"2023-01") -> 0 | C4: =SUMIFS(Trades!$X$2:$X$884,Trades!$F$2:$F$884,"2023-02") -> 0 | D4: =SUMIFS(Trades!$X$2:$X$884,Trades!$F$2:$F$884,"2023-03") -> 0 | E4: =SUMIFS(Trades!$X$2:$X$884,Trades!$F$2:$F$884,"2023-04") -> -638.22 | F4: =SUMIFS(Trades!$X$2:$X$884,Trades!$F$2:$F$884,"2023-05") -> -25.49 | G4: =SUMIFS(Trades!$X$2:$X$884,Trades!$F$2:$F$884,"2023-06") -> 1177.99 | H4: =SUMIFS(Trades!$X$2:$X$884,Trades!$F$2:$F$884,"2023-07") -> 343.27 | I4: =SUMIFS(Trades!$X$2:$X$884,Trades!$F$2:$F$884,"2023-08") -> 883.52 | J4: =SUMIFS(Trades!$X$2:$X$884,Trades!$F$2:$F$884,"2023-09") -> 1438.95 | K4: =SUMIFS(Trades!$X$2:$X$884,Trades!$F$2:$F$884,"2023-10") -> 990.48 | L4: =SUMIFS(Trades!$X$2:$X$884,Trades!$F$2:$F$884,"2023-11") -> 724.77 | M4: =SUMIFS(Trades!$X$2:$X$884,Trades!$F$2:$F$884,"2023-12") -> -428.62 | N4: =SUM(B4:M4) -> 4466.65 | O4: =IFERROR(N4/Summary!$C$5,0) -> 0.0446665
A5: 2024 | B5: =SUMIFS(Trades!$X$2:$X$884,Trades!$F$2:$F$884,"2024-01") -> 1010.77 | C5: =SUMIFS(Trades!$X$2:$X$884,Trades!$F$2:$F$884,"2024-02") -> 1018.44 | D5: =SUMIFS(Trades!$X$2:$X$884,Trades!$F$2:$F$884,"2024-03") -> -618.59 | E5: =SUMIFS(Trades!$X$2:$X$884,Trades!$F$2:$F$884,"2024-04") -> -540.62 | F5: =SUMIFS(Trades!$X$2:$X$884,Trades!$F$2:$F$884,"2024-05") -> 298.78 | G5: =SUMIFS(Trades!$X$2:$X$884,Trades!$F$2:$F$884,"2024-06") -> 79.97 | H5: =SUMIFS(Trades!$X$2:$X$884,Trades!$F$2:$F$884,"2024-07") -> 344.55 | I5: =SUMIFS(Trades!$X$2:$X$884,Trades!$F$2:$F$884,"2024-08") -> 173.58 | J5: =SUMIFS(Trades!$X$2:$X$884,Trades!$F$2:$F$884,"2024-09") -> -290 | K5: =SUMIFS(Trades!$X$2:$X$884,Trades!$F$2:$F$884,"2024-10") -> -328 | L5: =SUMIFS(Trades!$X$2:$X$884,Trades!$F$2:$F$884,"2024-11") -> 341.46 | M5: =SUMIFS(Trades!$X$2:$X$884,Trades!$F$2:$F$884,"2024-12") -> 884.68 | N5: =SUM(B5:M5) -> 2375.02 | O5: =IFERROR(N5/Summary!$C$5,0) -> 0.0237502
A6: 2025 | B6: =SUMIFS(Trades!$X$2:$X$884,Trades!$F$2:$F$884,"2025-01") -> 1042.63 | C6: =SUMIFS(Trades!$X$2:$X$884,Trades!$F$2:$F$884,"2025-02") -> 268.75 | D6: =SUMIFS(Trades!$X$2:$X$884,Trades!$F$2:$F$884,"2025-03") -> 709.31 | E6: =SUMIFS(Trades!$X$2:$X$884,Trades!$F$2:$F$884,"2025-04") -> 2501.59 | F6: =SUMIFS(Trades!$X$2:$X$884,Trades!$F$2:$F$884,"2025-05") -> 358.91 | G6: =SUMIFS(Trades!$X$2:$X$884,Trades!$F$2:$F$884,"2025-06") -> 345.34 | H6: =SUMIFS(Trades!$X$2:$X$884,Trades!$F$2:$F$884,"2025-07") -> 836.53 | I6: =SUMIFS(Trades!$X$2:$X$884,Trades!$F$2:$F$884,"2025-08") -> -140.64 | J6: =SUMIFS(Trades!$X$2:$X$884,Trades!$F$2:$F$884,"2025-09") -> -95.91 | K6: =SUMIFS(Trades!$X$2:$X$884,Trades!$F$2:$F$884,"2025-10") -> 1221.66 | L6: =SUMIFS(Trades!$X$2:$X$884,Trades!$F$2:$F$884,"2025-11") -> 923.27 | M6: =SUMIFS(Trades!$X$2:$X$884,Trades!$F$2:$F$884,"2025-12") -> -746.08 | N6: =SUM(B6:M6) -> 7225.36 | O6: =IFERROR(N6/Summary!$C$5,0) -> 0.0722536
A7: 2026 | B7: =SUMIFS(Trades!$X$2:$X$884,Trades!$F$2:$F$884,"2026-01") -> 487.9 | C7: =SUMIFS(Trades!$X$2:$X$884,Trades!$F$2:$F$884,"2026-02") -> 1186.81 | D7: =SUMIFS(Trades!$X$2:$X$884,Trades!$F$2:$F$884,"2026-03") -> -321.11 | E7: =SUMIFS(Trades!$X$2:$X$884,Trades!$F$2:$F$884,"2026-04") -> -129 | F7: =SUMIFS(Trades!$X$2:$X$884,Trades!$F$2:$F$884,"2026-05") -> 810.02 | G7: =SUMIFS(Trades!$X$2:$X$884,Trades!$F$2:$F$884,"2026-06") -> -589.22 | H7: =SUMIFS(Trades!$X$2:$X$884,Trades!$F$2:$F$884,"2026-07") -> -175.57 | I7: =SUMIFS(Trades!$X$2:$X$884,Trades!$F$2:$F$884,"2026-08") -> 1274.4 | J7: =SUMIFS(Trades!$X$2:$X$884,Trades!$F$2:$F$884,"2026-09") -> 1106.43 | K7: =SUMIFS(Trades!$X$2:$X$884,Trades!$F$2:$F$884,"2026-10") -> 0 | L7: =SUMIFS(Trades!$X$2:$X$884,Trades!$F$2:$F$884,"2026-11") -> 0 | M7: =SUMIFS(Trades!$X$2:$X$884,Trades!$F$2:$F$884,"2026-12") -> 0 | N7: =SUM(B7:M7) -> 3650.66 | O7: =IFERROR(N7/Summary!$C$5,0) -> 0.0365066
A9: Trades per month
A10: Year | B10: Jan | C10: Feb | D10: Mar | E10: Apr | F10: May | G10: Jun | H10: Jul | I10: Aug | J10: Sep | K10: Oct | L10: Nov | M10: Dec | N10: Year total
A11: 2023 | B11: =COUNTIFS(Trades!$F$2:$F$884,"2023-01") -> 0 | C11: =COUNTIFS(Trades!$F$2:$F$884,"2023-02") -> 0 | D11: =COUNTIFS(Trades!$F$2:$F$884,"2023-03") -> 0 | E11: =COUNTIFS(Trades!$F$2:$F$884,"2023-04") -> 18 | F11: =COUNTIFS(Trades!$F$2:$F$884,"2023-05") -> 25 | G11: =COUNTIFS(Trades!$F$2:$F$884,"2023-06") -> 21 | H11: =COUNTIFS(Trades!$F$2:$F$884,"2023-07") -> 22 | I11: =COUNTIFS(Trades!$F$2:$F$884,"2023-08") -> 25 | J11: =COUNTIFS(Trades!$F$2:$F$884,"2023-09") -> 21 | K11: =COUNTIFS(Trades!$F$2:$F$884,"2023-10") -> 21 | L11: =COUNTIFS(Trades!$F$2:$F$884,"2023-11") -> 22 | M11: =COUNTIFS(Trades!$F$2:$F$884,"2023-12") -> 19 | N11: =SUM(B11:M11) -> 194
A12: 2024 | B12: =COUNTIFS(Trades!$F$2:$F$884,"2024-01") -> 22 | C12: =COUNTIFS(Trades!$F$2:$F$884,"2024-02") -> 19 | D12: =COUNTIFS(Trades!$F$2:$F$884,"2024-03") -> 19 | E12: =COUNTIFS(Trades!$F$2:$F$884,"2024-04") -> 23 | F12: =COUNTIFS(Trades!$F$2:$F$884,"2024-05") -> 22 | G12: =COUNTIFS(Trades!$F$2:$F$884,"2024-06") -> 17 | H12: =COUNTIFS(Trades!$F$2:$F$884,"2024-07") -> 21 | I12: =COUNTIFS(Trades!$F$2:$F$884,"2024-08") -> 22 | J12: =COUNTIFS(Trades!$F$2:$F$884,"2024-09") -> 21 | K12: =COUNTIFS(Trades!$F$2:$F$884,"2024-10") -> 21 | L12: =COUNTIFS(Trades!$F$2:$F$884,"2024-11") -> 18 | M12: =COUNTIFS(Trades!$F$2:$F$884,"2024-12") -> 19 | N12: =SUM(B12:M12) -> 244
A13: 2025 | B13: =COUNTIFS(Trades!$F$2:$F$884,"2025-01") -> 20 | C13: =COUNTIFS(Trades!$F$2:$F$884,"2025-02") -> 20 | D13: =COUNTIFS(Trades!$F$2:$F$884,"2025-03") -> 21 | E13: =COUNTIFS(Trades!$F$2:$F$884,"2025-04") -> 19 | F13: =COUNTIFS(Trades!$F$2:$F$884,"2025-05") -> 24 | G13: =COUNTIFS(Trades!$F$2:$F$884,"2025-06") -> 21 | H13: =COUNTIFS(Trades!$F$2:$F$884,"2025-07") -> 23 | I13: =COUNTIFS(Trades!$F$2:$F$884,"2025-08") -> 21 | J13: =COUNTIFS(Trades!$F$2:$F$884,"2025-09") -> 19 | K13: =COUNTIFS(Trades!$F$2:$F$884,"2025-10") -> 27 | L13: =COUNTIFS(Trades!$F$2:$F$884,"2025-11") -> 19 | M13: =COUNTIFS(Trades!$F$2:$F$884,"2025-12") -> 23 | N13: =SUM(B13:M13) -> 257
A14: 2026 | B14: =COUNTIFS(Trades!$F$2:$F$884,"2026-01") -> 21 | C14: =COUNTIFS(Trades!$F$2:$F$884,"2026-02") -> 22 | D14: =COUNTIFS(Trades!$F$2:$F$884,"2026-03") -> 23 | E14: =COUNTIFS(Trades!$F$2:$F$884,"2026-04") -> 21 | F14: =COUNTIFS(Trades!$F$2:$F$884,"2026-05") -> 21 | G14: =COUNTIFS(Trades!$F$2:$F$884,"2026-06") -> 22 | H14: =COUNTIFS(Trades!$F$2:$F$884,"2026-07") -> 20 | I14: =COUNTIFS(Trades!$F$2:$F$884,"2026-08") -> 18 | J14: =COUNTIFS(Trades!$F$2:$F$884,"2026-09") -> 20 | K14: =COUNTIFS(Trades!$F$2:$F$884,"2026-10") -> 0 | L14: =COUNTIFS(Trades!$F$2:$F$884,"2026-11") -> 0 | M14: =COUNTIFS(Trades!$F$2:$F$884,"2026-12") -> 0 | N14: =SUM(B14:M14) -> 188
A16: Win rate per month
A17: Year | B17: Jan | C17: Feb | D17: Mar | E17: Apr | F17: May | G17: Jun | H17: Jul | I17: Aug | J17: Sep | K17: Oct | L17: Nov | M17: Dec
A18: 2023 | B18: =IFERROR(COUNTIFS(Trades!$F$2:$F$884,"2023-01",Trades!$Z$2:$Z$884,"Win")/COUNTIFS(Trades!$F$2:$F$884,"2023-01"),"") | C18: =IFERROR(COUNTIFS(Trades!$F$2:$F$884,"2023-02",Trades!$Z$2:$Z$884,"Win")/COUNTIFS(Trades!$F$2:$F$884,"2023-02"),"") | D18: =IFERROR(COUNTIFS(Trades!$F$2:$F$884,"2023-03",Trades!$Z$2:$Z$884,"Win")/COUNTIFS(Trades!$F$2:$F$884,"2023-03"),"") | E18: =IFERROR(COUNTIFS(Trades!$F$2:$F$884,"2023-04",Trades!$Z$2:$Z$884,"Win")/COUNTIFS(Trades!$F$2:$F$884,"2023-04"),"") -> 0.27777778 | F18: =IFERROR(COUNTIFS(Trades!$F$2:$F$884,"2023-05",Trades!$Z$2:$Z$884,"Win")/COUNTIFS(Trades!$F$2:$F$884,"2023-05"),"") -> 0.24 | G18: =IFERROR(COUNTIFS(Trades!$F$2:$F$884,"2023-06",Trades!$Z$2:$Z$884,"Win")/COUNTIFS(Trades!$F$2:$F$884,"2023-06"),"") -> 0.42857143 | H18: =IFERROR(COUNTIFS(Trades!$F$2:$F$884,"2023-07",Trades!$Z$2:$Z$884,"Win")/COUNTIFS(Trades!$F$2:$F$884,"2023-07"),"") -> 0.40909091 | I18: =IFERROR(COUNTIFS(Trades!$F$2:$F$884,"2023-08",Trades!$Z$2:$Z$884,"Win")/COUNTIFS(Trades!$F$2:$F$884,"2023-08"),"") -> 0.36 | J18: =IFERROR(COUNTIFS(Trades!$F$2:$F$884,"2023-09",Trades!$Z$2:$Z$884,"Win")/COUNTIFS(Trades!$F$2:$F$884,"2023-09"),"") -> 0.33333333 | K18: =IFERROR(COUNTIFS(Trades!$F$2:$F$884,"2023-10",Trades!$Z$2:$Z$884,"Win")/COUNTIFS(Trades!$F$2:$F$884,"2023-10"),"") -> 0.38095238 | L18: =IFERROR(COUNTIFS(Trades!$F$2:$F$884,"2023-11",Trades!$Z$2:$Z$884,"Win")/COUNTIFS(Trades!$F$2:$F$884,"2023-11"),"") -> 0.36363636 | M18: =IFERROR(COUNTIFS(Trades!$F$2:$F$884,"2023-12",Trades!$Z$2:$Z$884,"Win")/COUNTIFS(Trades!$F$2:$F$884,"2023-12"),"") -> 0.21052632
A19: 2024 | B19: =IFERROR(COUNTIFS(Trades!$F$2:$F$884,"2024-01",Trades!$Z$2:$Z$884,"Win")/COUNTIFS(Trades!$F$2:$F$884,"2024-01"),"") -> 0.45454545 | C19: =IFERROR(COUNTIFS(Trades!$F$2:$F$884,"2024-02",Trades!$Z$2:$Z$884,"Win")/COUNTIFS(Trades!$F$2:$F$884,"2024-02"),"") -> 0.26315789 | D19: =IFERROR(COUNTIFS(Trades!$F$2:$F$884,"2024-03",Trades!$Z$2:$Z$884,"Win")/COUNTIFS(Trades!$F$2:$F$884,"2024-03"),"") -> 0.26315789 | E19: =IFERROR(COUNTIFS(Trades!$F$2:$F$884,"2024-04",Trades!$Z$2:$Z$884,"Win")/COUNTIFS(Trades!$F$2:$F$884,"2024-04"),"") -> 0.2173913 | F19: =IFERROR(COUNTIFS(Trades!$F$2:$F$884,"2024-05",Trades!$Z$2:$Z$884,"Win")/COUNTIFS(Trades!$F$2:$F$884,"2024-05"),"") -> 0.31818182 | G19: =IFERROR(COUNTIFS(Trades!$F$2:$F$884,"2024-06",Trades!$Z$2:$Z$884,"Win")/COUNTIFS(Trades!$F$2:$F$884,"2024-06"),"") -> 0.29411765 | H19: =IFERROR(COUNTIFS(Trades!$F$2:$F$884,"2024-07",Trades!$Z$2:$Z$884,"Win")/COUNTIFS(Trades!$F$2:$F$884,"2024-07"),"") -> 0.33333333 | I19: =IFERROR(COUNTIFS(Trades!$F$2:$F$884,"2024-08",Trades!$Z$2:$Z$884,"Win")/COUNTIFS(Trades!$F$2:$F$884,"2024-08"),"") -> 0.31818182 | J19: =IFERROR(COUNTIFS(Trades!$F$2:$F$884,"2024-09",Trades!$Z$2:$Z$884,"Win")/COUNTIFS(Trades!$F$2:$F$884,"2024-09"),"") -> 0.23809524 | K19: =IFERROR(COUNTIFS(Trades!$F$2:$F$884,"2024-10",Trades!$Z$2:$Z$884,"Win")/COUNTIFS(Trades!$F$2:$F$884,"2024-10"),"") -> 0.23809524 | L19: =IFERROR(COUNTIFS(Trades!$F$2:$F$884,"2024-11",Trades!$Z$2:$Z$884,"Win")/COUNTIFS(Trades!$F$2:$F$884,"2024-11"),"") -> 0.33333333 | M19: =IFERROR(COUNTIFS(Trades!$F$2:$F$884,"2024-12",Trades!$Z$2:$Z$884,"Win")/COUNTIFS(Trades!$F$2:$F$884,"2024-12"),"") -> 0.31578947
A20: 2025 | B20: =IFERROR(COUNTIFS(Trades!$F$2:$F$884,"2025-01",Trades!$Z$2:$Z$884,"Win")/COUNTIFS(Trades!$F$2:$F$884,"2025-01"),"") -> 0.35 | C20: =IFERROR(COUNTIFS(Trades!$F$2:$F$884,"2025-02",Trades!$Z$2:$Z$884,"Win")/COUNTIFS(Trades!$F$2:$F$884,"2025-02"),"") -> 0.45 | D20: =IFERROR(COUNTIFS(Trades!$F$2:$F$884,"2025-03",Trades!$Z$2:$Z$884,"Win")/COUNTIFS(Trades!$F$2:$F$884,"2025-03"),"") -> 0.23809524 | E20: =IFERROR(COUNTIFS(Trades!$F$2:$F$884,"2025-04",Trades!$Z$2:$Z$884,"Win")/COUNTIFS(Trades!$F$2:$F$884,"2025-04"),"") -> 0.26315789 | F20: =IFERROR(COUNTIFS(Trades!$F$2:$F$884,"2025-05",Trades!$Z$2:$Z$884,"Win")/COUNTIFS(Trades!$F$2:$F$884,"2025-05"),"") -> 0.33333333 | G20: =IFERROR(COUNTIFS(Trades!$F$2:$F$884,"2025-06",Trades!$Z$2:$Z$884,"Win")/COUNTIFS(Trades!$F$2:$F$884,"2025-06"),"") -> 0.38095238 | H20: =IFERROR(COUNTIFS(Trades!$F$2:$F$884,"2025-07",Trades!$Z$2:$Z$884,"Win")/COUNTIFS(Trades!$F$2:$F$884,"2025-07"),"") -> 0.39130435 | I20: =IFERROR(COUNTIFS(Trades!$F$2:$F$884,"2025-08",Trades!$Z$2:$Z$884,"Win")/COUNTIFS(Trades!$F$2:$F$884,"2025-08"),"") -> 0.19047619 | J20: =IFERROR(COUNTIFS(Trades!$F$2:$F$884,"2025-09",Trades!$Z$2:$Z$884,"Win")/COUNTIFS(Trades!$F$2:$F$884,"2025-09"),"") -> 0.26315789 | K20: =IFERROR(COUNTIFS(Trades!$F$2:$F$884,"2025-10",Trades!$Z$2:$Z$884,"Win")/COUNTIFS(Trades!$F$2:$F$884,"2025-10"),"") -> 0.40740741 | L20: =IFERROR(COUNTIFS(Trades!$F$2:$F$884,"2025-11",Trades!$Z$2:$Z$884,"Win")/COUNTIFS(Trades!$F$2:$F$884,"2025-11"),"") -> 0.47368421 | M20: =IFERROR(COUNTIFS(Trades!$F$2:$F$884,"2025-12",Trades!$Z$2:$Z$884,"Win")/COUNTIFS(Trades!$F$2:$F$884,"2025-12"),"") -> 0.17391304
A21: 2026 | B21: =IFERROR(COUNTIFS(Trades!$F$2:$F$884,"2026-01",Trades!$Z$2:$Z$884,"Win")/COUNTIFS(Trades!$F$2:$F$884,"2026-01"),"") -> 0.33333333 | C21: =IFERROR(COUNTIFS(Trades!$F$2:$F$884,"2026-02",Trades!$Z$2:$Z$884,"Win")/COUNTIFS(Trades!$F$2:$F$884,"2026-02"),"") -> 0.31818182 | D21: =IFERROR(COUNTIFS(Trades!$F$2:$F$884,"2026-03",Trades!$Z$2:$Z$884,"Win")/COUNTIFS(Trades!$F$2:$F$884,"2026-03"),"") -> 0.26086957 | E21: =IFERROR(COUNTIFS(Trades!$F$2:$F$884,"2026-04",Trades!$Z$2:$Z$884,"Win")/COUNTIFS(Trades!$F$2:$F$884,"2026-04"),"") -> 0.42857143 | F21: =IFERROR(COUNTIFS(Trades!$F$2:$F$884,"2026-05",Trades!$Z$2:$Z$884,"Win")/COUNTIFS(Trades!$F$2:$F$884,"2026-05"),"") -> 0.33333333 | G21: =IFERROR(COUNTIFS(Trades!$F$2:$F$884,"2026-06",Trades!$Z$2:$Z$884,"Win")/COUNTIFS(Trades!$F$2:$F$884,"2026-06"),"") -> 0.18181818 | H21: =IFERROR(COUNTIFS(Trades!$F$2:$F$884,"2026-07",Trades!$Z$2:$Z$884,"Win")/COUNTIFS(Trades!$F$2:$F$884,"2026-07"),"") -> 0.2 | I21: =IFERROR(COUNTIFS(Trades!$F$2:$F$884,"2026-08",Trades!$Z$2:$Z$884,"Win")/COUNTIFS(Trades!$F$2:$F$884,"2026-08"),"") -> 0.38888889 | J21: =IFERROR(COUNTIFS(Trades!$F$2:$F$884,"2026-09",Trades!$Z$2:$Z$884,"Win")/COUNTIFS(Trades!$F$2:$F$884,"2026-09"),"") -> 0.45 | K21: =IFERROR(COUNTIFS(Trades!$F$2:$F$884,"2026-10",Trades!$Z$2:$Z$884,"Win")/COUNTIFS(Trades!$F$2:$F$884,"2026-10"),"") | L21: =IFERROR(COUNTIFS(Trades!$F$2:$F$884,"2026-11",Trades!$Z$2:$Z$884,"Win")/COUNTIFS(Trades!$F$2:$F$884,"2026-11"),"") | M21: =IFERROR(COUNTIFS(Trades!$F$2:$F$884,"2026-12",Trades!$Z$2:$Z$884,"Win")/COUNTIFS(Trades!$F$2:$F$884,"2026-12"),"")

Sheet Weekly
A1: Week (Mon) | B1: Trades | C1: Wins | D1: Losses | E1: Win rate | F1: Net profit | G1: Gross profit | H1: Gross loss | I1: Profit factor | J1: Best trade | K1: Worst trade | L1: Total R | M1: Start balance | N1: Return % | O1: Limit check | P1: End balance | Q1: Cumulative net
A2: 45019 | B2: =COUNTIFS(Trades!$E$2:$E$884,$A2) -> 3 | C2: =COUNTIFS(Trades!$E$2:$E$884,$A2,Trades!$Z$2:$Z$884,"Win") -> 2 | D2: =COUNTIFS(Trades!$E$2:$E$884,$A2,Trades!$Z$2:$Z$884,"Loss") -> 1 | E2: =IFERROR(C2/B2,0) -> 0.66666667 | F2: =SUMIFS(Trades!$X$2:$X$884,Trades!$E$2:$E$884,$A2) -> 224.34 | G2: =SUMIFS(Trades!$X$2:$X$884,Trades!$E$2:$E$884,$A2,Trades!$X$2:$X$884,">0") -> 226.24 | H2: =SUMIFS(Trades!$X$2:$X$884,Trades!$E$2:$E$884,$A2,Trades!$X$2:$X$884,"<0") -> -1.9 | I2: =IFERROR(G2/-H2,"no loss") -> 119.07368 | J2: =_xlfn.MAXIFS(Trades!$X$2:$X$884,Trades!$E$2:$E$884,$A2) -> 140.56 | K2: =_xlfn.MINIFS(Trades!$X$2:$X$884,Trades!$E$2:$E$884,$A2) -> -1.9 | L2: =SUMIFS(Trades!$Y$2:$Y$884,Trades!$E$2:$E$884,$A2) -> 4.0614034 | M2: =Summary!$C$5 -> 100000 | N2: =IFERROR(F2/M2,0) -> 0.0022434 | O2: =IF(F2<0,"down week","") | P2: =M2+F2 -> 100224.34 | Q2: =P2-Summary!$C$5 -> 224.34
A3: 45026 | B3: =COUNTIFS(Trades!$E$2:$E$884,$A3) -> 7 | C3: =COUNTIFS(Trades!$E$2:$E$884,$A3,Trades!$Z$2:$Z$884,"Win") -> 1 | D3: =COUNTIFS(Trades!$E$2:$E$884,$A3,Trades!$Z$2:$Z$884,"Loss") -> 6 | E3: =IFERROR(C3/B3,0) -> 0.14285714 | F3: =SUMIFS(Trades!$X$2:$X$884,Trades!$E$2:$E$884,$A3) -> -619.87 | G3: =SUMIFS(Trades!$X$2:$X$884,Trades!$E$2:$E$884,$A3,Trades!$X$2:$X$884,">0") -> 60.72 | H3: =SUMIFS(Trades!$X$2:$X$884,Trades!$E$2:$E$884,$A3,Trades!$X$2:$X$884,"<0") -> -680.59 | I3: =IFERROR(G3/-H3,"no loss") -> 0.089216709 | J3: =_xlfn.MAXIFS(Trades!$X$2:$X$884,Trades!$E$2:$E$884,$A3) -> 60.72 | K3: =_xlfn.MINIFS(Trades!$X$2:$X$884,Trades!$E$2:$E$884,$A3) -> -354.48 | L3: =SUMIFS(Trades!$Y$2:$Y$884,Trades!$E$2:$E$884,$A3) -> -4.1516873 | M3: =P2 -> 100224.34 | N3: =IFERROR(F3/M3,0) -> -0.006184825 | O3: =IF(F3<0,"down week","") -> down week | P3: =M3+F3 -> 99604.47 | Q3: =P3-Summary!$C$5 -> -395.53
A4: 45033 | B4: =COUNTIFS(Trades!$E$2:$E$884,$A4) -> 4 | C4: =COUNTIFS(Trades!$E$2:$E$884,$A4,Trades!$Z$2:$Z$884,"Win") -> 2 | D4: =COUNTIFS(Trades!$E$2:$E$884,$A4,Trades!$Z$2:$Z$884,"Loss") -> 2 | E4: =IFERROR(C4/B4,0) -> 0.5 | F4: =SUMIFS(Trades!$X$2:$X$884,Trades!$E$2:$E$884,$A4) -> 151.09 | G4: =SUMIFS(Trades!$X$2:$X$884,Trades!$E$2:$E$884,$A4,Trades!$X$2:$X$884,">0") -> 294.03 | H4: =SUMIFS(Trades!$X$2:$X$884,Trades!$E$2:$E$884,$A4,Trades!$X$2:$X$884,"<0") -> -142.94 | I4: =IFERROR(G4/-H4,"no loss") -> 2.0570169 | J4: =_xlfn.MAXIFS(Trades!$X$2:$X$884,Trades!$E$2:$E$884,$A4) -> 170.07 | K4: =_xlfn.MINIFS(Trades!$X$2:$X$884,Trades!$E$2:$E$884,$A4) -> -71.54 | L4: =SUMIFS(Trades!$Y$2:$Y$884,Trades!$E$2:$E$884,$A4) -> 2.0501535 | M4: =P3 -> 99604.47 | N4: =IFERROR(F4/M4,0) -> 0.0015168998 | O4: =IF(F4<0,"down week","") | P4: =M4+F4 -> 99755.56 | Q4: =P4-Summary!$C$5 -> -244.44
A5: 45040 | B5: =COUNTIFS(Trades!$E$2:$E$884,$A5) -> 4 | C5: =COUNTIFS(Trades!$E$2:$E$884,$A5,Trades!$Z$2:$Z$884,"Win") -> 0 | D5: =COUNTIFS(Trades!$E$2:$E$884,$A5,Trades!$Z$2:$Z$884,"Loss") -> 4 | E5: =IFERROR(C5/B5,0) -> 0 | F5: =SUMIFS(Trades!$X$2:$X$884,Trades!$E$2:$E$884,$A5) -> -393.78 | G5: =SUMIFS(Trades!$X$2:$X$884,Trades!$E$2:$E$884,$A5,Trades!$X$2:$X$884,">0") -> 0 | H5: =SUMIFS(Trades!$X$2:$X$884,Trades!$E$2:$E$884,$A5,Trades!$X$2:$X$884,"<0") -> -393.78 | I5: =IFERROR(G5/-H5,"no loss") -> 0 | J5: =_xlfn.MAXIFS(Trades!$X$2:$X$884,Trades!$E$2:$E$884,$A5) -> -12.92 | K5: =_xlfn.MINIFS(Trades!$X$2:$X$884,Trades!$E$2:$E$884,$A5) -> -209.98 | L5: =SUMIFS(Trades!$Y$2:$Y$884,Trades!$E$2:$E$884,$A5) -> -3.2375505 | M5: =P4 -> 99755.56 | N5: =IFERROR(F5/M5,0) -> -0.0039474491 | O5: =IF(F5<0,"down week","") -> down week | P5: =M5+F5 -> 99361.78 | Q5: =P5-Summary!$C$5 -> -638.22
A6: 45047 | B6: =COUNTIFS(Trades!$E$2:$E$884,$A6) -> 5 | C6: =COUNTIFS(Trades!$E$2:$E$884,$A6,Trades!$Z$2:$Z$884,"Win") -> 2 | D6: =COUNTIFS(Trades!$E$2:$E$884,$A6,Trades!$Z$2:$Z$884,"Loss") -> 3 | E6: =IFERROR(C6/B6,0) -> 0.4 | F6: =SUMIFS(Trades!$X$2:$X$884,Trades!$E$2:$E$884,$A6) -> 296.44 | G6: =SUMIFS(Trades!$X$2:$X$884,Trades!$E$2:$E$884,$A6,Trades!$X$2:$X$884,">0") -> 545.52 | H6: =SUMIFS(Trades!$X$2:$X$884,Trades!$E$2:$E$884,$A6,Trades!$X$2:$X$884,"<0") -> -249.08 | I6: =IFERROR(G6/-H6,"no loss") -> 2.1901397 | J6: =_xlfn.MAXIFS(Trades!$X$2:$X$884,Trades!$E$2:$E$884,$A6) -> 310.99 | K6: =_xlfn.MINIFS(Trades!$X$2:$X$884,Trades!$E$2:$E$884,$A6) -> -171.35 | L6: =SUMIFS(Trades!$Y$2:$Y$884,Trades!$E$2:$E$884,$A6) -> 1.2329055 | M6: =P5 -> 99361.78 | N6: =IFERROR(F6/M6,0) -> 0.0029834409 | O6: =IF(F6<0,"down week","") | P6: =M6+F6 -> 99658.22 | Q6: =P6-Summary!$C$5 -> -341.78
A7: 45054 | B7: =COUNTIFS(Trades!$E$2:$E$884,$A7) -> 6 | C7: =COUNTIFS(Trades!$E$2:$E$884,$A7,Trades!$Z$2:$Z$884,"Win") -> 2 | D7: =COUNTIFS(Trades!$E$2:$E$884,$A7,Trades!$Z$2:$Z$884,"Loss") -> 4 | E7: =IFERROR(C7/B7,0) -> 0.33333333 | F7: =SUMIFS(Trades!$X$2:$X$884,Trades!$E$2:$E$884,$A7) -> 259.25 | G7: =SUMIFS(Trades!$X$2:$X$884,Trades!$E$2:$E$884,$A7,Trades!$X$2:$X$884,">0") -> 484.31 | H7: =SUMIFS(Trades!$X$2:$X$884,Trades!$E$2:$E$884,$A7,Trades!$X$2:$X$884,"<0") -> -225.06 | I7: =IFERROR(G7/-H7,"no loss") -> 2.151915 | J7: =_xlfn.MAXIFS(Trades!$X$2:$X$884,Trades!$E$2:$E$884,$A7) -> 316.67 | K7: =_xlfn.MINIFS(Trades!$X$2:$X$884,Trades!$E$2:$E$884,$A7) -> -68.05 | L7: =SUMIFS(Trades!$Y$2:$Y$884,Trades!$E$2:$E$884,$A7) -> -0.21620756 | M7: =P6 -> 99658.22 | N7: =IFERROR(F7/M7,0) -> 0.002601391 | O7: =IF(F7<0,"down week","") | P7: =M7+F7 -> 99917.47 | Q7: =P7-Summary!$C$5 -> -82.53
A8: 45061 | B8: =COUNTIFS(Trades!$E$2:$E$884,$A8) -> 4 | C8: =COUNTIFS(Trades!$E$2:$E$884,$A8,Trades!$Z$2:$Z$884,"Win") -> 1 | D8: =COUNTIFS(Trades!$E$2:$E$884,$A8,Trades!$Z$2:$Z$884,"Loss") -> 3 | E8: =IFERROR(C8/B8,0) -> 0.25 | F8: =SUMIFS(Trades!$X$2:$X$884,Trades!$E$2:$E$884,$A8) -> -5.4 | G8: =SUMIFS(Trades!$X$2:$X$884,Trades!$E$2:$E$884,$A8,Trades!$X$2:$X$884,">0") -> 128.45 | H8: =SUMIFS(Trades!$X$2:$X$884,Trades!$E$2:$E$884,$A8,Trades!$X$2:$X$884,"<0") -> -133.85 | I8: =IFERROR(G8/-H8,"no loss") -> 0.95965633 | J8: =_xlfn.MAXIFS(Trades!$X$2:$X$884,Trades!$E$2:$E$884,$A8) -> 128.45 | K8: =_xlfn.MINIFS(Trades!$X$2:$X$884,Trades!$E$2:$E$884,$A8) -> -70.03 | L8: =SUMIFS(Trades!$Y$2:$Y$884,Trades!$E$2:$E$884,$A8) -> 0.66966437 | M8: =P7 -> 99917.47 | N8: =IFERROR(F8/M8,0) -> -5.4044603e-05 | O8: =IF(F8<0,"down week","") -> down week | P8: =M8+F8 -> 99912.07 | Q8: =P8-Summary!$C$5 -> -87.93
A9: 45068 | B9: =COUNTIFS(Trades!$E$2:$E$884,$A9) -> 6 | C9: =COUNTIFS(Trades!$E$2:$E$884,$A9,Trades!$Z$2:$Z$884,"Win") -> 0 | D9: =COUNTIFS(Trades!$E$2:$E$884,$A9,Trades!$Z$2:$Z$884,"Loss") -> 6 | E9: =IFERROR(C9/B9,0) -> 0 | F9: =SUMIFS(Trades!$X$2:$X$884,Trades!$E$2:$E$884,$A9) -> -543.22 | G9: =SUMIFS(Trades!$X$2:$X$884,Trades!$E$2:$E$884,$A9,Trades!$X$2:$X$884,">0") -> 0 | H9: =SUMIFS(Trades!$X$2:$X$884,Trades!$E$2:$E$884,$A9,Trades!$X$2:$X$884,"<0") -> -543.22 | I9: =IFERROR(G9/-H9,"no loss") -> 0 | J9: =_xlfn.MAXIFS(Trades!$X$2:$X$884,Trades!$E$2:$E$884,$A9) -> -2.05 | K9: =_xlfn.MINIFS(Trades!$X$2:$X$884,Trades!$E$2:$E$884,$A9) -> -365.06 | L9: =SUMIFS(Trades!$Y$2:$Y$884,Trades!$E$2:$E$884,$A9) -> -4.1468431 | M9: =P8 -> 99912.07 | N9: =IFERROR(F9/M9,0) -> -0.0054369807 | O9: =IF(F9<0,"down week","") -> down week | P9: =M9+F9 -> 99368.85 | Q9: =P9-Summary!$C$5 -> -631.15
A10: 45075 | B10: =COUNTIFS(Trades!$E$2:$E$884,$A10) -> 7 | C10: =COUNTIFS(Trades!$E$2:$E$884,$A10,Trades!$Z$2:$Z$884,"Win") -> 3 | D10: =COUNTIFS(Trades!$E$2:$E$884,$A10,Trades!$Z$2:$Z$884,"Loss") -> 4 | E10: =IFERROR(C10/B10,0) -> 0.42857143 | F10: =SUMIFS(Trades!$X$2:$X$884,Trades!$E$2:$E$884,$A10) -> 90.26 | G10: =SUMIFS(Trades!$X$2:$X$884,Trades!$E$2:$E$884,$A10,Trades!$X$2:$X$884,">0") -> 401.5 | H10: =SUMIFS(Trades!$X$2:$X$884,Trades!$E$2:$E$884,$A10,Trades!$X$2:$X$884,"<0") -> -311.24 | I10: =IFERROR(G10/-H10,"no loss") -> 1.2900013 | J10: =_xlfn.MAXIFS(Trades!$X$2:$X$884,Trades!$E$2:$E$884,$A10) -> 157.36 | K10: =_xlfn.MINIFS(Trades!$X$2:$X$884,Trades!$E$2:$E$884,$A10) -> -133.3 | L10: =SUMIFS(Trades!$Y$2:$Y$884,Trades!$E$2:$E$884,$A10) -> 3.9163363 | M10: =P9 -> 99368.85 | N10: =IFERROR(F10/M10,0) -> 0.00090833294 | O10: =IF(F10<0,"down week","") | P10: =M10+F10 -> 99459.11 | Q10: =P10-Summary!$C$5 -> -540.89
A11: 45082 | B11: =COUNTIFS(Trades!$E$2:$E$884,$A11) -> 5 | C11: =COUNTIFS(Trades!$E$2:$E$884,$A11,Trades!$Z$2:$Z$884,"Win") -> 2 | D11: =COUNTIFS(Trades!$E$2:$E$884,$A11,Trades!$Z$2:$Z$884,"Loss") -> 3 | E11: =IFERROR(C11/B11,0) -> 0.4 | F11: =SUMIFS(Trades!$X$2:$X$884,Trades!$E$2:$E$884,$A11) -> 216.76 | G11: =SUMIFS(Trades!$X$2:$X$884,Trades!$E$2:$E$884,$A11,Trades!$X$2:$X$884,">0") -> 266.14 | H11: =SUMIFS(Trades!$X$2:$X$884,Trades!$E$2:$E$884,$A11,Trades!$X$2:$X$884,"<0") -> -49.38 | I11: =IFERROR(G11/-H11,"no loss") -> 5.3896314 | J11: =_xlfn.MAXIFS(Trades!$X$2:$X$884,Trades!$E$2:$E$884,$A11) -> 175.62 | K11: =_xlfn.MINIFS(Trades!$X$2:$X$884,Trades!$E$2:$E$884,$A11) -> -48 | L11: =SUMIFS(Trades!$Y$2:$Y$884,Trades!$E$2:$E$884,$A11) -> 3.5580984 | M11: =P10 -> 99459.11 | N11: =IFERROR(F11/M11,0) -> 0.0021793881 | O11: =IF(F11<0,"down week","") | P11: =M11+F11 -> 99675.87 | Q11: =P11-Summary!$C$5 -> -324.13
A12: 45089 | B12: =COUNTIFS(Trades!$E$2:$E$884,$A12) -> 5 | C12: =COUNTIFS(Trades!$E$2:$E$884,$A12,Trades!$Z$2:$Z$884,"Win") -> 1 | D12: =COUNTIFS(Trades!$E$2:$E$884,$A12,Trades!$Z$2:$Z$884,"Loss") -> 4 | E12: =IFERROR(C12/B12,0) -> 0.2 | F12: =SUMIFS(Trades!$X$2:$X$884,Trades!$E$2:$E$884,$A12) -> -68.47 | G12: =SUMIFS(Trades!$X$2:$X$884,Trades!$E$2:$E$884,$A12,Trades!$X$2:$X$884,">0") -> 110.82 | H12: =SUMIFS(Trades!$X$2:$X$884,Trades!$E$2:$E$884,$A12,Trades!$X$2:$X$884,"<0") -> -179.29 | I12: =IFERROR(G12/-H12,"no loss") -> 0.61810475 | J12: =_xlfn.MAXIFS(Trades!$X$2:$X$884,Trades!$E$2:$E$884,$A12) -> 110.82 | K12: =_xlfn.MINIFS(Trades!$X$2:$X$884,Trades!$E$2:$E$884,$A12) -> -110.94 | L12: =SUMIFS(Trades!$Y$2:$Y$884,Trades!$E$2:$E$884,$A12) -> -0.055908415 | M12: =P11 -> 99675.87 | N12: =IFERROR(F12/M12,0) -> -0.00068692653 | O12: =IF(F12<0,"down week","") -> down week | P12: =M12+F12 -> 99607.4 | Q12: =P12-Summary!$C$5 -> -392.6
A13: 45096 | B13: =COUNTIFS(Trades!$E$2:$E$884,$A13) -> 5 | C13: =COUNTIFS(Trades!$E$2:$E$884,$A13,Trades!$Z$2:$Z$884,"Win") -> 1 | D13: =COUNTIFS(Trades!$E$2:$E$884,$A13,Trades!$Z$2:$Z$884,"Loss") -> 4 | E13: =IFERROR(C13/B13,0) -> 0.2 | F13: =SUMIFS(Trades!$X$2:$X$884,Trades!$E$2:$E$884,$A13) -> 111.7 | G13: =SUMIFS(Trades!$X$2:$X$884,Trades!$E$2:$E$884,$A13,Trades!$X$2:$X$884,">0") -> 255.61 | H13: =SUMIFS(Trades!$X$2:$X$884,Trades!$E$2:$E$884,$A13,Trades!$X$2:$X$884,"<0") -> -143.91 | I13: =IFERROR(G13/-H13,"no loss") -> 1.7761796 | J13: =_xlfn.MAXIFS(Trades!$X$2:$X$884,Trades!$E$2:$E$884,$A13) -> 255.61 | K13: =_xlfn.MINIFS(Trades!$X$2:$X$884,Trades!$E$2:$E$884,$A13) -> -56.55 | L13: =SUMIFS(Trades!$Y$2:$Y$884,Trades!$E$2:$E$884,$A13) -> -1.1203487 | M13: =P12 -> 99607.4 | N13: =IFERROR(F13/M13,0) -> 0.0011214026 | O13: =IF(F13<0,"down week","") | P13: =M13+F13 -> 99719.1 | Q13: =P13-Summary!$C$5 -> -280.9
A14: 45103 | B14: =COUNTIFS(Trades!$E$2:$E$884,$A14) -> 3 | C14: =COUNTIFS(Trades!$E$2:$E$884,$A14,Trades!$Z$2:$Z$884,"Win") -> 3 | D14: =COUNTIFS(Trades!$E$2:$E$884,$A14,Trades!$Z$2:$Z$884,"Loss") -> 0 | E14: =IFERROR(C14/B14,0) -> 1 | F14: =SUMIFS(Trades!$X$2:$X$884,Trades!$E$2:$E$884,$A14) -> 795.18 | G14: =SUMIFS(Trades!$X$2:$X$884,Trades!$E$2:$E$884,$A14,Trades!$X$2:$X$884,">0") -> 795.18 | H14: =SUMIFS(Trades!$X$2:$X$884,Trades!$E$2:$E$884,$A14,Trades!$X$2:$X$884,"<0") -> 0 | I14: =IFERROR(G14/-H14,"no loss") -> no loss | J14: =_xlfn.MAXIFS(Trades!$X$2:$X$884,Trades!$E$2:$E$884,$A14) -> 313.44 | K14: =_xlfn.MINIFS(Trades!$X$2:$X$884,Trades!$E$2:$E$884,$A14) -> 180.3 | L14: =SUMIFS(Trades!$Y$2:$Y$884,Trades!$E$2:$E$884,$A14) -> 6.0266209 | M14: =P13 -> 99719.1 | N14: =IFERROR(F14/M14,0) -> 0.0079741995 | O14: =IF(F14<0,"down week","") | P14: =M14+F14 -> 100514.28 | Q14: =P14-Summary!$C$5 -> 514.28
... A183: 46286 | B183: =COUNTIFS(Trades!$E$2:$E$884,$A183) -> 6 | C183: =COUNTIFS(Trades!$E$2:$E$884,$A183,Trades!$Z$2:$Z$884,"Win") -> 3 | D183: =COUNTIFS(Trades!$E$2:$E$884,$A183,Trades!$Z$2:$Z$884,"Loss") -> 3 | E183: =IFERROR(C183/B183,0) -> 0.5 | F183: =SUMIFS(Trades!$X$2:$X$884,Trades!$E$2:$E$884,$A183) -> 70.85 | G183: =SUMIFS(Trades!$X$2:$X$884,Trades!$E$2:$E$884,$A183,Trades!$X$2:$X$884,">0") -> 293.45 | H183: =SUMIFS(Trades!$X$2:$X$884,Trades!$E$2:$E$884,$A183,Trades!$X$2:$X$884,"<0") -> -222.6 | I183: =IFERROR(G183/-H183,"no loss") -> 1.3182839 | J183: =_xlfn.MAXIFS(Trades!$X$2:$X$884,Trades!$E$2:$E$884,$A183) -> 111.11 | K183: =_xlfn.MINIFS(Trades!$X$2:$X$884,Trades!$E$2:$E$884,$A183) -> -180.88 | L183: =SUMIFS(Trades!$Y$2:$Y$884,Trades!$E$2:$E$884,$A183) -> 4.2587431 | M183: =P182 -> 117646.84 | N183: =IFERROR(F183/M183,0) -> 0.00060222612 | O183: =IF(F183<0,"down week","") | P183: =M183+F183 -> 117717.69 | Q183: =P183-Summary!$C$5 -> 17717.69
A185: TOTAL | B185: =SUM(B2:B183) -> 883 | C185: =SUM(C2:C183) -> 282 | D185: =SUM(D2:D183) -> 593 | E185: =IFERROR(C185/B185,0) -> 0.3193658 | F185: =SUM(F2:F183) -> 17717.69 | G185: =SUM(G2:G183) -> 64334.51 | H185: =SUM(H2:H183) -> -46616.82 | I185: =IFERROR(G185/-H185,0) -> 1.3800708 | L185: =SUM(L2:L183) -> 176.66944 | N185: =IFERROR(F185/M2,0) -> 0.1771769 | O185: =COUNTIF(F2:F183,">0")&" up / "&COUNTIF(F2:F183,"<0")&" down" -> 102 up / 80 down

Sheet Daily
A1: Date | B1: Trades | C1: Wins | D1: Losses | E1: Win rate | F1: Net profit | G1: Gross profit | H1: Gross loss | I1: Profit factor | J1: Best trade | K1: Worst trade | L1: Total R | M1: Start balance | N1: Return % | O1: Limit check | P1: End balance | Q1: Cumulative net | R1: Weekday
A2: 45020 | B2: =COUNTIFS(Trades!$D$2:$D$884,$A2) -> 1 | C2: =COUNTIFS(Trades!$D$2:$D$884,$A2,Trades!$Z$2:$Z$884,"Win") -> 1 | D2: =COUNTIFS(Trades!$D$2:$D$884,$A2,Trades!$Z$2:$Z$884,"Loss") -> 0 | E2: =IFERROR(C2/B2,0) -> 1 | F2: =SUMIFS(Trades!$X$2:$X$884,Trades!$D$2:$D$884,$A2) -> 85.68 | G2: =SUMIFS(Trades!$X$2:$X$884,Trades!$D$2:$D$884,$A2,Trades!$X$2:$X$884,">0") -> 85.68 | H2: =SUMIFS(Trades!$X$2:$X$884,Trades!$D$2:$D$884,$A2,Trades!$X$2:$X$884,"<0") -> 0 | I2: =IFERROR(G2/-H2,"no loss") -> no loss | J2: =_xlfn.MAXIFS(Trades!$X$2:$X$884,Trades!$D$2:$D$884,$A2) -> 85.68 | K2: =_xlfn.MINIFS(Trades!$X$2:$X$884,Trades!$D$2:$D$884,$A2) -> 85.68 | L2: =SUMIFS(Trades!$Y$2:$Y$884,Trades!$D$2:$D$884,$A2) -> 2.038835 | M2: =Summary!$C$5 -> 100000 | N2: =IFERROR(F2/M2,0) -> 0.0008568 | O2: =IF(-N2>=Summary!$C$7,"BREACH","") | P2: =M2+F2 -> 100085.68 | Q2: =P2-Summary!$C$5 -> 85.68 | R2: =TEXT(A2,"ddd") -> Tue
A3: 45021 | B3: =COUNTIFS(Trades!$D$2:$D$884,$A3) -> 1 | C3: =COUNTIFS(Trades!$D$2:$D$884,$A3,Trades!$Z$2:$Z$884,"Win") -> 0 | D3: =COUNTIFS(Trades!$D$2:$D$884,$A3,Trades!$Z$2:$Z$884,"Loss") -> 1 | E3: =IFERROR(C3/B3,0) -> 0 | F3: =SUMIFS(Trades!$X$2:$X$884,Trades!$D$2:$D$884,$A3) -> -1.9 | G3: =SUMIFS(Trades!$X$2:$X$884,Trades!$D$2:$D$884,$A3,Trades!$X$2:$X$884,">0") -> 0 | H3: =SUMIFS(Trades!$X$2:$X$884,Trades!$D$2:$D$884,$A3,Trades!$X$2:$X$884,"<0") -> -1.9 | I3: =IFERROR(G3/-H3,"no loss") -> 0 | J3: =_xlfn.MAXIFS(Trades!$X$2:$X$884,Trades!$D$2:$D$884,$A3) -> -1.9 | K3: =_xlfn.MINIFS(Trades!$X$2:$X$884,Trades!$D$2:$D$884,$A3) -> -1.9 | L3: =SUMIFS(Trades!$Y$2:$Y$884,Trades!$D$2:$D$884,$A3) -> -0.013942703 | M3: =P2 -> 100085.68 | N3: =IFERROR(F3/M3,0) -> -1.8983735e-05 | O3: =IF(-N3>=Summary!$C$7,"BREACH","") | P3: =M3+F3 -> 100083.78 | Q3: =P3-Summary!$C$5 -> 83.78 | R3: =TEXT(A3,"ddd") -> Wed
A4: 45022 | B4: =COUNTIFS(Trades!$D$2:$D$884,$A4) -> 1 | C4: =COUNTIFS(Trades!$D$2:$D$884,$A4,Trades!$Z$2:$Z$884,"Win") -> 1 | D4: =COUNTIFS(Trades!$D$2:$D$884,$A4,Trades!$Z$2:$Z$884,"Loss") -> 0 | E4: =IFERROR(C4/B4,0) -> 1 | F4: =SUMIFS(Trades!$X$2:$X$884,Trades!$D$2:$D$884,$A4) -> 140.56 | G4: =SUMIFS(Trades!$X$2:$X$884,Trades!$D$2:$D$884,$A4,Trades!$X$2:$X$884,">0") -> 140.56 | H4: =SUMIFS(Trades!$X$2:$X$884,Trades!$D$2:$D$884,$A4,Trades!$X$2:$X$884,"<0") -> 0 | I4: =IFERROR(G4/-H4,"no loss") -> no loss | J4: =_xlfn.MAXIFS(Trades!$X$2:$X$884,Trades!$D$2:$D$884,$A4) -> 140.56 | K4: =_xlfn.MINIFS(Trades!$X$2:$X$884,Trades!$D$2:$D$884,$A4) -> 140.56 | L4: =SUMIFS(Trades!$Y$2:$Y$884,Trades!$D$2:$D$884,$A4) -> 2.0365112 | M4: =P3 -> 100083.78 | N4: =IFERROR(F4/M4,0) -> 0.0014044234 | O4: =IF(-N4>=Summary!$C$7,"BREACH","") | P4: =M4+F4 -> 100224.34 | Q4: =P4-Summary!$C$5 -> 224.34 | R4: =TEXT(A4,"ddd") -> Thu
A5: 45026 | B5: =COUNTIFS(Trades!$D$2:$D$884,$A5) -> 2 | C5: =COUNTIFS(Trades!$D$2:$D$884,$A5,Trades!$Z$2:$Z$884,"Win") -> 1 | D5: =COUNTIFS(Trades!$D$2:$D$884,$A5,Trades!$Z$2:$Z$884,"Loss") -> 1 | E5: =IFERROR(C5/B5,0) -> 0.5 | F5: =SUMIFS(Trades!$X$2:$X$884,Trades!$D$2:$D$884,$A5) -> -8.57 | G5: =SUMIFS(Trades!$X$2:$X$884,Trades!$D$2:$D$884,$A5,Trades!$X$2:$X$884,">0") -> 60.72 | H5: =SUMIFS(Trades!$X$2:$X$884,Trades!$D$2:$D$884,$A5,Trades!$X$2:$X$884,"<0") -> -69.29 | I5: =IFERROR(G5/-H5,"no loss") -> 0.87631693 | J5: =_xlfn.MAXIFS(Trades!$X$2:$X$884,Trades!$D$2:$D$884,$A5) -> 60.72 | K5: =_xlfn.MINIFS(Trades!$X$2:$X$884,Trades!$D$2:$D$884,$A5) -> -69.29 | L5: =SUMIFS(Trades!$Y$2:$Y$884,Trades!$D$2:$D$884,$A5) -> 1.0441183 | M5: =P4 -> 100224.34 | N5: =IFERROR(F5/M5,0) -> -8.5508171e-05 | O5: =IF(-N5>=Summary!$C$7,"BREACH","") | P5: =M5+F5 -> 100215.77 | Q5: =P5-Summary!$C$5 -> 215.77 | R5: =TEXT(A5,"ddd") -> Mon
A6: 45027 | B6: =COUNTIFS(Trades!$D$2:$D$884,$A6) -> 1 | C6: =COUNTIFS(Trades!$D$2:$D$884,$A6,Trades!$Z$2:$Z$884,"Win") -> 0 | D6: =COUNTIFS(Trades!$D$2:$D$884,$A6,Trades!$Z$2:$Z$884,"Loss") -> 1 | E6: =IFERROR(C6/B6,0) -> 0 | F6: =SUMIFS(Trades!$X$2:$X$884,Trades!$D$2:$D$884,$A6) -> -35.36 | G6: =SUMIFS(Trades!$X$2:$X$884,Trades!$D$2:$D$884,$A6,Trades!$X$2:$X$884,">0") -> 0 | H6: =SUMIFS(Trades!$X$2:$X$884,Trades!$D$2:$D$884,$A6,Trades!$X$2:$X$884,"<0") -> -35.36 | I6: =IFERROR(G6/-H6,"no loss") -> 0 | J6: =_xlfn.MAXIFS(Trades!$X$2:$X$884,Trades!$D$2:$D$884,$A6) -> -35.36 | K6: =_xlfn.MINIFS(Trades!$X$2:$X$884,Trades!$D$2:$D$884,$A6) -> -35.36 | L6: =SUMIFS(Trades!$Y$2:$Y$884,Trades!$D$2:$D$884,$A6) -> -1.0116732 | M6: =P5 -> 100215.77 | N6: =IFERROR(F6/M6,0) -> -0.00035283868 | O6: =IF(-N6>=Summary!$C$7,"BREACH","") | P6: =M6+F6 -> 100180.41 | Q6: =P6-Summary!$C$5 -> 180.41 | R6: =TEXT(A6,"ddd") -> Tue
A7: 45028 | B7: =COUNTIFS(Trades!$D$2:$D$884,$A7) -> 2 | C7: =COUNTIFS(Trades!$D$2:$D$884,$A7,Trades!$Z$2:$Z$884,"Win") -> 0 | D7: =COUNTIFS(Trades!$D$2:$D$884,$A7,Trades!$Z$2:$Z$884,"Loss") -> 2 | E7: =IFERROR(C7/B7,0) -> 0 | F7: =SUMIFS(Trades!$X$2:$X$884,Trades!$D$2:$D$884,$A7) -> -401.81 | G7: =SUMIFS(Trades!$X$2:$X$884,Trades!$D$2:$D$884,$A7,Trades!$X$2:$X$884,">0") -> 0 | H7: =SUMIFS(Trades!$X$2:$X$884,Trades!$D$2:$D$884,$A7,Trades!$X$2:$X$884,"<0") -> -401.81 | I7: =IFERROR(G7/-H7,"no loss") -> 0 | J7: =_xlfn.MAXIFS(Trades!$X$2:$X$884,Trades!$D$2:$D$884,$A7) -> -47.33 | K7: =_xlfn.MINIFS(Trades!$X$2:$X$884,Trades!$D$2:$D$884,$A7) -> -354.48 | L7: =SUMIFS(Trades!$Y$2:$Y$884,Trades!$D$2:$D$884,$A7) -> -2.0316835 | M7: =P6 -> 100180.41 | N7: =IFERROR(F7/M7,0) -> -0.004010864 | O7: =IF(-N7>=Summary!$C$7,"BREACH","") | P7: =M7+F7 -> 99778.6 | Q7: =P7-Summary!$C$5 -> -221.4 | R7: =TEXT(A7,"ddd") -> Wed
A8: 45029 | B8: =COUNTIFS(Trades!$D$2:$D$884,$A8) -> 1 | C8: =COUNTIFS(Trades!$D$2:$D$884,$A8,Trades!$Z$2:$Z$884,"Win") -> 0 | D8: =COUNTIFS(Trades!$D$2:$D$884,$A8,Trades!$Z$2:$Z$884,"Loss") -> 1 | E8: =IFERROR(C8/B8,0) -> 0 | F8: =SUMIFS(Trades!$X$2:$X$884,Trades!$D$2:$D$884,$A8) -> -34.93 | G8: =SUMIFS(Trades!$X$2:$X$884,Trades!$D$2:$D$884,$A8,Trades!$X$2:$X$884,">0") -> 0 | H8: =SUMIFS(Trades!$X$2:$X$884,Trades!$D$2:$D$884,$A8,Trades!$X$2:$X$884,"<0") -> -34.93 | I8: =IFERROR(G8/-H8,"no loss") -> 0 | J8: =_xlfn.MAXIFS(Trades!$X$2:$X$884,Trades!$D$2:$D$884,$A8) -> -34.93 | K8: =_xlfn.MINIFS(Trades!$X$2:$X$884,Trades!$D$2:$D$884,$A8) -> -34.93 | L8: =SUMIFS(Trades!$Y$2:$Y$884,Trades!$D$2:$D$884,$A8) -> -1.1064302 | M8: =P7 -> 99778.6 | N8: =IFERROR(F8/M8,0) -> -0.00035007507 | O8: =IF(-N8>=Summary!$C$7,"BREACH","") | P8: =M8+F8 -> 99743.67 | Q8: =P8-Summary!$C$5 -> -256.33 | R8: =TEXT(A8,"ddd") -> Thu
A9: 45030 | B9: =COUNTIFS(Trades!$D$2:$D$884,$A9) -> 1 | C9: =COUNTIFS(Trades!$D$2:$D$884,$A9,Trades!$Z$2:$Z$884,"Win") -> 0 | D9: =COUNTIFS(Trades!$D$2:$D$884,$A9,Trades!$Z$2:$Z$884,"Loss") -> 1 | E9: =IFERROR(C9/B9,0) -> 0 | F9: =SUMIFS(Trades!$X$2:$X$884,Trades!$D$2:$D$884,$A9) -> -139.2 | G9: =SUMIFS(Trades!$X$2:$X$884,Trades!$D$2:$D$884,$A9,Trades!$X$2:$X$884,">0") -> 0 | H9: =SUMIFS(Trades!$X$2:$X$884,Trades!$D$2:$D$884,$A9,Trades!$X$2:$X$884,"<0") -> -139.2 | I9: =IFERROR(G9/-H9,"no loss") -> 0 | J9: =_xlfn.MAXIFS(Trades!$X$2:$X$884,Trades!$D$2:$D$884,$A9) -> -139.2 | K9: =_xlfn.MINIFS(Trades!$X$2:$X$884,Trades!$D$2:$D$884,$A9) -> -139.2 | L9: =SUMIFS(Trades!$Y$2:$Y$884,Trades!$D$2:$D$884,$A9) -> -1.0460188 | M9: =P8 -> 99743.67 | N9: =IFERROR(F9/M9,0) -> -0.0013955773 | O9: =IF(-N9>=Summary!$C$7,"BREACH","") | P9: =M9+F9 -> 99604.47 | Q9: =P9-Summary!$C$5 -> -395.53 | R9: =TEXT(A9,"ddd") -> Fri
A10: 45034 | B10: =COUNTIFS(Trades!$D$2:$D$884,$A10) -> 1 | C10: =COUNTIFS(Trades!$D$2:$D$884,$A10,Trades!$Z$2:$Z$884,"Win") -> 0 | D10: =COUNTIFS(Trades!$D$2:$D$884,$A10,Trades!$Z$2:$Z$884,"Loss") -> 1 | E10: =IFERROR(C10/B10,0) -> 0 | F10: =SUMIFS(Trades!$X$2:$X$884,Trades!$D$2:$D$884,$A10) -> -71.54 | G10: =SUMIFS(Trades!$X$2:$X$884,Trades!$D$2:$D$884,$A10,Trades!$X$2:$X$884,">0") -> 0 | H10: =SUMIFS(Trades!$X$2:$X$884,Trades!$D$2:$D$884,$A10,Trades!$X$2:$X$884,"<0") -> -71.54 | I10: =IFERROR(G10/-H10,"no loss") -> 0 | J10: =_xlfn.MAXIFS(Trades!$X$2:$X$884,Trades!$D$2:$D$884,$A10) -> -71.54 | K10: =_xlfn.MINIFS(Trades!$X$2:$X$884,Trades!$D$2:$D$884,$A10) -> -71.54 | L10: =SUMIFS(Trades!$Y$2:$Y$884,Trades!$D$2:$D$884,$A10) -> -1.0145215 | M10: =P9 -> 99604.47 | N10: =IFERROR(F10/M10,0) -> -0.00071824086 | O10: =IF(-N10>=Summary!$C$7,"BREACH","") | P10: =M10+F10 -> 99532.93 | Q10: =P10-Summary!$C$5 -> -467.07 | R10: =TEXT(A10,"ddd") -> Tue
A11: 45035 | B11: =COUNTIFS(Trades!$D$2:$D$884,$A11) -> 1 | C11: =COUNTIFS(Trades!$D$2:$D$884,$A11,Trades!$Z$2:$Z$884,"Win") -> 1 | D11: =COUNTIFS(Trades!$D$2:$D$884,$A11,Trades!$Z$2:$Z$884,"Loss") -> 0 | E11: =IFERROR(C11/B11,0) -> 1 | F11: =SUMIFS(Trades!$X$2:$X$884,Trades!$D$2:$D$884,$A11) -> 123.96 | G11: =SUMIFS(Trades!$X$2:$X$884,Trades!$D$2:$D$884,$A11,Trades!$X$2:$X$884,">0") -> 123.96 | H11: =SUMIFS(Trades!$X$2:$X$884,Trades!$D$2:$D$884,$A11,Trades!$X$2:$X$884,"<0") -> 0 | I11: =IFERROR(G11/-H11,"no loss") -> no loss | J11: =_xlfn.MAXIFS(Trades!$X$2:$X$884,Trades!$D$2:$D$884,$A11) -> 123.96 | K11: =_xlfn.MINIFS(Trades!$X$2:$X$884,Trades!$D$2:$D$884,$A11) -> 123.96 | L11: =SUMIFS(Trades!$Y$2:$Y$884,Trades!$D$2:$D$884,$A11) -> 2.043656 | M11: =P10 -> 99532.93 | N11: =IFERROR(F11/M11,0) -> 0.001245417 | O11: =IF(-N11>=Summary!$C$7,"BREACH","") | P11: =M11+F11 -> 99656.89 | Q11: =P11-Summary!$C$5 -> -343.11 | R11: =TEXT(A11,"ddd") -> Wed
A12: 45036 | B12: =COUNTIFS(Trades!$D$2:$D$884,$A12) -> 1 | C12: =COUNTIFS(Trades!$D$2:$D$884,$A12,Trades!$Z$2:$Z$884,"Win") -> 1 | D12: =COUNTIFS(Trades!$D$2:$D$884,$A12,Trades!$Z$2:$Z$884,"Loss") -> 0 | E12: =IFERROR(C12/B12,0) -> 1 | F12: =SUMIFS(Trades!$X$2:$X$884,Trades!$D$2:$D$884,$A12) -> 170.07 | G12: =SUMIFS(Trades!$X$2:$X$884,Trades!$D$2:$D$884,$A12,Trades!$X$2:$X$884,">0") -> 170.07 | H12: =SUMIFS(Trades!$X$2:$X$884,Trades!$D$2:$D$884,$A12,Trades!$X$2:$X$884,"<0") -> 0 | I12: =IFERROR(G12/-H12,"no loss") -> no loss | J12: =_xlfn.MAXIFS(Trades!$X$2:$X$884,Trades!$D$2:$D$884,$A12) -> 170.07 | K12: =_xlfn.MINIFS(Trades!$X$2:$X$884,Trades!$D$2:$D$884,$A12) -> 170.07 | L12: =SUMIFS(Trades!$Y$2:$Y$884,Trades!$D$2:$D$884,$A12) -> 2.0267661 | M12: =P11 -> 99656.89 | N12: =IFERROR(F12/M12,0) -> 0.0017065554 | O12: =IF(-N12>=Summary!$C$7,"BREACH","") | P12: =M12+F12 -> 99826.96 | Q12: =P12-Summary!$C$5 -> -173.04 | R12: =TEXT(A12,"ddd") -> Thu
A13: 45037 | B13: =COUNTIFS(Trades!$D$2:$D$884,$A13) -> 1 | C13: =COUNTIFS(Trades!$D$2:$D$884,$A13,Trades!$Z$2:$Z$884,"Win") -> 0 | D13: =COUNTIFS(Trades!$D$2:$D$884,$A13,Trades!$Z$2:$Z$884,"Loss") -> 1 | E13: =IFERROR(C13/B13,0) -> 0 | F13: =SUMIFS(Trades!$X$2:$X$884,Trades!$D$2:$D$884,$A13) -> -71.4 | G13: =SUMIFS(Trades!$X$2:$X$884,Trades!$D$2:$D$884,$A13,Trades!$X$2:$X$884,">0") -> 0 | H13: =SUMIFS(Trades!$X$2:$X$884,Trades!$D$2:$D$884,$A13,Trades!$X$2:$X$884,"<0") -> -71.4 | I13: =IFERROR(G13/-H13,"no loss") -> 0 | J13: =_xlfn.MAXIFS(Trades!$X$2:$X$884,Trades!$D$2:$D$884,$A13) -> -71.4 | K13: =_xlfn.MINIFS(Trades!$X$2:$X$884,Trades!$D$2:$D$884,$A13) -> -71.4 | L13: =SUMIFS(Trades!$Y$2:$Y$884,Trades!$D$2:$D$884,$A13) -> -1.0057471 | M13: =P12 -> 99826.96 | N13: =IFERROR(F13/M13,0) -> -0.00071523765 | O13: =IF(-N13>=Summary!$C$7,"BREACH","") | P13: =M13+F13 -> 99755.56 | Q13: =P13-Summary!$C$5 -> -244.44 | R13: =TEXT(A13,"ddd") -> Fri
A14: 45040 | B14: =COUNTIFS(Trades!$D$2:$D$884,$A14) -> 2 | C14: =COUNTIFS(Trades!$D$2:$D$884,$A14,Trades!$Z$2:$Z$884,"Win") -> 0 | D14: =COUNTIFS(Trades!$D$2:$D$884,$A14,Trades!$Z$2:$Z$884,"Loss") -> 2 | E14: =IFERROR(C14/B14,0) -> 0 | F14: =SUMIFS(Trades!$X$2:$X$884,Trades!$D$2:$D$884,$A14) -> -299.6 | G14: =SUMIFS(Trades!$X$2:$X$884,Trades!$D$2:$D$884,$A14,Trades!$X$2:$X$884,">0") -> 0 | H14: =SUMIFS(Trades!$X$2:$X$884,Trades!$D$2:$D$884,$A14,Trades!$X$2:$X$884,"<0") -> -299.6 | I14: =IFERROR(G14/-H14,"no loss") -> 0 | J14: =_xlfn.MAXIFS(Trades!$X$2:$X$884,Trades!$D$2:$D$884,$A14) -> -89.62 | K14: =_xlfn.MINIFS(Trades!$X$2:$X$884,Trades!$D$2:$D$884,$A14) -> -209.98 | L14: =SUMIFS(Trades!$Y$2:$Y$884,Trades!$D$2:$D$884,$A14) -> -2.0138463 | M14: =P13 -> 99755.56 | N14: =IFERROR(F14/M14,0) -> -0.0030033414 | O14: =IF(-N14>=Summary!$C$7,"BREACH","") | P14: =M14+F14 -> 99455.96 | Q14: =P14-Summary!$C$5 -> -544.04 | R14: =TEXT(A14,"ddd") -> Mon
... A777: 46290 | B777: =COUNTIFS(Trades!$D$2:$D$884,$A777) -> 1 | C777: =COUNTIFS(Trades!$D$2:$D$884,$A777,Trades!$Z$2:$Z$884,"Win") -> 1 | D777: =COUNTIFS(Trades!$D$2:$D$884,$A777,Trades!$Z$2:$Z$884,"Loss") -> 0 | E777: =IFERROR(C777/B777,0) -> 1 | F777: =SUMIFS(Trades!$X$2:$X$884,Trades!$D$2:$D$884,$A777) -> 111.11 | G777: =SUMIFS(Trades!$X$2:$X$884,Trades!$D$2:$D$884,$A777,Trades!$X$2:$X$884,">0") -> 111.11 | H777: =SUMIFS(Trades!$X$2:$X$884,Trades!$D$2:$D$884,$A777,Trades!$X$2:$X$884,"<0") -> 0 | I777: =IFERROR(G777/-H777,"no loss") -> no loss | J777: =_xlfn.MAXIFS(Trades!$X$2:$X$884,Trades!$D$2:$D$884,$A777) -> 111.11 | K777: =_xlfn.MINIFS(Trades!$X$2:$X$884,Trades!$D$2:$D$884,$A777) -> 111.11 | L777: =SUMIFS(Trades!$Y$2:$Y$884,Trades!$D$2:$D$884,$A777) -> 2.0048719 | M777: =P776 -> 117606.58 | N777: =IFERROR(F777/M777,0) -> 0.00094476006 | O777: =IF(-N777>=Summary!$C$7,"BREACH","") | P777: =M777+F777 -> 117717.69 | Q777: =P777-Summary!$C$5 -> 17717.69 | R777: =TEXT(A777,"ddd") -> Fri
A779: TOTAL | B779: =SUM(B2:B777) -> 883 | C779: =SUM(C2:C777) -> 282 | D779: =SUM(D2:D777) -> 593 | E779: =IFERROR(C779/B779,0) -> 0.3193658 | F779: =SUM(F2:F777) -> 17717.69 | G779: =SUM(G2:G777) -> 64334.51 | H779: =SUM(H2:H777) -> -46616.82 | I779: =IFERROR(G779/-H779,0) -> 1.3800708 | L779: =SUM(L2:L777) -> 176.66944 | N779: =IFERROR(F779/M2,0) -> 0.1771769 | O779: =COUNTIF(F2:F777,">0")&" up / "&COUNTIF(F2:F777,"<0")&" down" -> 265 up / 505 down

Sheet Trades
A1: # | B1: Entry time | C1: Close time | D1: Close date | E1: Week (Mon) | F1: Month | G1: Year | H1: Weekday | I1: Entry hour | J1: Side | K1: Setup | L1: Lots | M1: Entry price | N1: Initial SL | O1: Take profit | P1: SL distance (pts) | Q1: TP distance (pts) | R1: Planned risk $ | S1: Exit price | T1: Exit reason | U1: Points made | V1: Commission $ | W1: Swap $ | X1: Net profit $ | Y1: R multiple | Z1: Result | AA1: Hold (min) | AB1: Hold bucket | AC1: SL bucket (pts) | AD1: Balance after | AE1: Peak balance | AF1: Drawdown $ | AG1: Drawdown %
A2: 1 | B2: 45020.513 | C2: 45020.515 | D2: =INT(C2) -> 45020 | E2: =D2-WEEKDAY(D2,3) -> 45019 | F2: 2023-04 | G2: 2023 | H2: Tue | I2: 12 | J2: BUY | K2: PDH breakout | L2: 0.34 | M2: 13160.42 | N2: 13154.24 | O2: 13172.77 | P2: =ABS(M2-N2) -> 6.18 | Q2: =IF(O2="","",ABS(O2-M2)) -> 12.35 | R2: =P2*L2*Summary!$C$6 -> 42.024 | S2: 13173.02 | T2: Take profit | U2: =IF(J2="BUY",S2-M2,M2-S2) -> 12.6 | V2: 0 | W2: 0 | X2: 85.68 | Y2: =IFERROR(X2/R2,0) -> 2.038835 | Z2: =IF(X2>0,"Win",IF(X2<0,"Loss","Flat")) -> Win | AA2: =ROUND((C2-B2)*1440,1) -> 2.3 | AB2: =IF(AA2<1,"a) <1 min",IF(AA2<10,"b) 1-10 min",IF(AA2<60,"c) 10-60 min",IF(AA2<240,"d) 1-4 h","e) 4 h+")))) -> b) 1-10 min | AC2: =IF(P2<10,"a) <10",IF(P2<20,"b) 10-20",IF(P2<40,"c) 20-40",IF(P2<80,"d) 40-80","e) 80+")))) -> a) <10 | AD2: =Summary!$C$5+SUM(X$2:X2) -> 100085.68 | AE2: =MAX(Summary!$C$5,AD2) -> 100085.68 | AF2: =AE2-AD2 -> 0 | AG2: =IFERROR(AF2/AE2,0) -> 0
A3: 2 | B3: 45021.691 | C3: 45021.709 | D3: =INT(C3) -> 45021 | E3: =D3-WEEKDAY(D3,3) -> 45019 | F3: 2023-04 | G3: 2023 | H3: Wed | I3: 16 | J3: SELL | K3: PDL breakout | L3: 0.34 | M3: 13040.29 | N3: 13060.33 | O3: 13000.06 | P3: =ABS(M3-N3) -> 20.04 | Q3: =IF(O3="","",ABS(O3-M3)) -> 40.23 | R3: =P3*L3*Summary!$C$6 -> 136.272 | S3: 13040.57 | T3: Breakeven stop | U3: =IF(J3="BUY",S3-M3,M3-S3) -> -0.28 | V3: 0 | W3: 0 | X3: -1.9 | Y3: =IFERROR(X3/R3,0) -> -0.013942703 | Z3: =IF(X3>0,"Win",IF(X3<0,"Loss","Flat")) -> Loss | AA3: =ROUND((C3-B3)*1440,1) -> 25.8 | AB3: =IF(AA3<1,"a) <1 min",IF(AA3<10,"b) 1-10 min",IF(AA3<60,"c) 10-60 min",IF(AA3<240,"d) 1-4 h","e) 4 h+")))) -> c) 10-60 min | AC3: =IF(P3<10,"a) <10",IF(P3<20,"b) 10-20",IF(P3<40,"c) 20-40",IF(P3<80,"d) 40-80","e) 80+")))) -> c) 20-40 | AD3: =Summary!$C$5+SUM(X$2:X3) -> 100083.78 | AE3: =MAX(AE2,AD3) -> 100085.68 | AF3: =AE3-AD3 -> 1.9 | AG3: =IFERROR(AF3/AE3,0) -> 1.8983735e-05
A4: 3 | B4: 45022.541 | C4: 45022.544 | D4: =INT(C4) -> 45022 | E4: =D4-WEEKDAY(D4,3) -> 45019 | F4: 2023-04 | G4: 2023 | H4: Thu | I4: 12 | J4: SELL | K4: PDL breakout | L4: 0.34 | M4: 12891.4 | N4: 12901.55 | O4: 12871.13 | P4: =ABS(M4-N4) -> 10.15 | Q4: =IF(O4="","",ABS(O4-M4)) -> 20.27 | R4: =P4*L4*Summary!$C$6 -> 69.02 | S4: 12870.73 | T4: Take profit | U4: =IF(J4="BUY",S4-M4,M4-S4) -> 20.67 | V4: 0 | W4: 0 | X4: 140.56 | Y4: =IFERROR(X4/R4,0) -> 2.0365112 | Z4: =IF(X4>0,"Win",IF(X4<0,"Loss","Flat")) -> Win | AA4: =ROUND((C4-B4)*1440,1) -> 4 | AB4: =IF(AA4<1,"a) <1 min",IF(AA4<10,"b) 1-10 min",IF(AA4<60,"c) 10-60 min",IF(AA4<240,"d) 1-4 h","e) 4 h+")))) -> b) 1-10 min | AC4: =IF(P4<10,"a) <10",IF(P4<20,"b) 10-20",IF(P4<40,"c) 20-40",IF(P4<80,"d) 40-80","e) 80+")))) -> b) 10-20 | AD4: =Summary!$C$5+SUM(X$2:X4) -> 100224.34 | AE4: =MAX(AE3,AD4) -> 100224.34 | AF4: =AE4-AD4 -> 0 | AG4: =IFERROR(AF4/AE4,0) -> 0
A5: 4 | B5: 45026.053 | C5: 45026.057 | D5: =INT(C5) -> 45026 | E5: =D5-WEEKDAY(D5,3) -> 45026 | F5: 2023-04 | G5: 2023 | H5: Mon | I5: 1 | J5: BUY | K5: PDH breakout | L5: 0.34 | M5: 13086.8 | N5: 13076.65 | O5: 13107.1 | P5: =ABS(M5-N5) -> 10.15 | Q5: =IF(O5="","",ABS(O5-M5)) -> 20.3 | R5: =P5*L5*Summary!$C$6 -> 69.02 | S5: 13076.61 | T5: Initial stop loss | U5: =IF(J5="BUY",S5-M5,M5-S5) -> -10.19 | V5: 0 | W5: 0 | X5: -69.29 | Y5: =IFERROR(X5/R5,0) -> -1.0039119 | Z5: =IF(X5>0,"Win",IF(X5<0,"Loss","Flat")) -> Loss | AA5: =ROUND((C5-B5)*1440,1) -> 6.3 | AB5: =IF(AA5<1,"a) <1 min",IF(AA5<10,"b) 1-10 min",IF(AA5<60,"c) 10-60 min",IF(AA5<240,"d) 1-4 h","e) 4 h+")))) -> b) 1-10 min | AC5: =IF(P5<10,"a) <10",IF(P5<20,"b) 10-20",IF(P5<40,"c) 20-40",IF(P5<80,"d) 40-80","e) 80+")))) -> b) 10-20 | AD5: =Summary!$C$5+SUM(X$2:X5) -> 100155.05 | AE5: =MAX(AE4,AD5) -> 100224.34 | AF5: =AE5-AD5 -> 69.29 | AG5: =IFERROR(AF5/AE5,0) -> 0.00069134903
A6: 5 | B6: 45026.371 | C6: 45026.389 | D6: =INT(C6) -> 45026 | E6: =D6-WEEKDAY(D6,3) -> 45026 | F6: 2023-04 | G6: 2023 | H6: Mon | I6: 8 | J6: SELL | K6: PDL breakout | L6: 0.34 | M6: 13011.15 | N6: 13015.51 | O6: 13002.37 | P6: =ABS(M6-N6) -> 4.36 | Q6: =IF(O6="","",ABS(O6-M6)) -> 8.78 | R6: =P6*L6*Summary!$C$6 -> 29.648 | S6: 13002.22 | T6: Take profit | U6: =IF(J6="BUY",S6-M6,M6-S6) -> 8.93 | V6: 0 | W6: 0 | X6: 60.72 | Y6: =IFERROR(X6/R6,0) -> 2.0480302 | Z6: =IF(X6>0,"Win",IF(X6<0,"Loss","Flat")) -> Win | AA6: =ROUND((C6-B6)*1440,1) -> 26.7 | AB6: =IF(AA6<1,"a) <1 min",IF(AA6<10,"b) 1-10 min",IF(AA6<60,"c) 10-60 min",IF(AA6<240,"d) 1-4 h","e) 4 h+")))) -> c) 10-60 min | AC6: =IF(P6<10,"a) <10",IF(P6<20,"b) 10-20",IF(P6<40,"c) 20-40",IF(P6<80,"d) 40-80","e) 80+")))) -> a) <10 | AD6: =Summary!$C$5+SUM(X$2:X6) -> 100215.77 | AE6: =MAX(AE5,AD6) -> 100224.34 | AF6: =AE6-AD6 -> 8.57 | AG6: =IFERROR(AF6/AE6,0) -> 8.5508171e-05
A7: 6 | B7: 45027.528 | C7: 45027.534 | D7: =INT(C7) -> 45027 | E7: =D7-WEEKDAY(D7,3) -> 45026 | F7: 2023-04 | G7: 2023 | H7: Tue | I7: 12 | J7: BUY | K7: PDH breakout | L7: 0.34 | M7: 13088.56 | N7: 13083.42 | O7: 13098.85 | P7: =ABS(M7-N7) -> 5.14 | Q7: =IF(O7="","",ABS(O7-M7)) -> 10.29 | R7: =P7*L7*Summary!$C$6 -> 34.952 | S7: 13083.36 | T7: Initial stop loss | U7: =IF(J7="BUY",S7-M7,M7-S7) -> -5.2 | V7: 0 | W7: 0 | X7: -35.36 | Y7: =IFERROR(X7/R7,0) -> -1.0116732 | Z7: =IF(X7>0,"Win",IF(X7<0,"Loss","Flat")) -> Loss | AA7: =ROUND((C7-B7)*1440,1) -> 7.7 | AB7: =IF(AA7<1,"a) <1 min",IF(AA7<10,"b) 1-10 min",IF(AA7<60,"c) 10-60 min",IF(AA7<240,"d) 1-4 h","e) 4 h+")))) -> b) 1-10 min | AC7: =IF(P7<10,"a) <10",IF(P7<20,"b) 10-20",IF(P7<40,"c) 20-40",IF(P7<80,"d) 40-80","e) 80+")))) -> a) <10 | AD7: =Summary!$C$5+SUM(X$2:X7) -> 100180.41 | AE7: =MAX(AE6,AD7) -> 100224.34 | AF7: =AE7-AD7 -> 43.93 | AG7: =IFERROR(AF7/AE7,0) -> 0.00043831668
A8: 7 | B8: 45028.394 | C8: 45028.407 | D8: =INT(C8) -> 45028 | E8: =D8-WEEKDAY(D8,3) -> 45026 | F8: 2023-04 | G8: 2023 | H8: Wed | I8: 9 | J8: SELL | K8: PDL breakout | L8: 0.34 | M8: 12942.33 | N8: 12949.13 | O8: 12928.88 | P8: =ABS(M8-N8) -> 6.8 | Q8: =IF(O8="","",ABS(O8-M8)) -> 13.45 | R8: =P8*L8*Summary!$C$6 -> 46.24 | S8: 12949.29 | T8: Initial stop loss | U8: =IF(J8="BUY",S8-M8,M8-S8) -> -6.96 | V8: 0 | W8: 0 | X8: -47.33 | Y8: =IFERROR(X8/R8,0) -> -1.0235727 | Z8: =IF(X8>0,"Win",IF(X8<0,"Loss","Flat")) -> Loss | AA8: =ROUND((C8-B8)*1440,1) -> 18.4 | AB8: =IF(AA8<1,"a) <1 min",IF(AA8<10,"b) 1-10 min",IF(AA8<60,"c) 10-60 min",IF(AA8<240,"d) 1-4 h","e) 4 h+")))) -> c) 10-60 min | AC8: =IF(P8<10,"a) <10",IF(P8<20,"b) 10-20",IF(P8<40,"c) 20-40",IF(P8<80,"d) 40-80","e) 80+")))) -> a) <10 | AD8: =Summary!$C$5+SUM(X$2:X8) -> 100133.08 | AE8: =MAX(AE7,AD8) -> 100224.34 | AF8: =AE8-AD8 -> 91.26 | AG8: =IFERROR(AF8/AE8,0) -> 0.00091055726
A9: 8 | B9: 45028.649 | C9: 45028.667 | D9: =INT(C9) -> 45028 | E9: =D9-WEEKDAY(D9,3) -> 45026 | F9: 2023-04 | G9: 2023 | H9: Wed | I9: 15 | J9: BUY | K9: PDH breakout | L9: 0.34 | M9: 13106.9 | N9: 13055.19 | O9: 13210.2 | P9: =ABS(M9-N9) -> 51.71 | Q9: =IF(O9="","",ABS(O9-M9)) -> 103.3 | R9: =P9*L9*Summary!$C$6 -> 351.628 | S9: 13054.77 | T9: Initial stop loss | U9: =IF(J9="BUY",S9-M9,M9-S9) -> -52.13 | V9: 0 | W9: 0 | X9: -354.48 | Y9: =IFERROR(X9/R9,0) -> -1.0081108 | Z9: =IF(X9>0,"Win",IF(X9<0,"Loss","Flat")) -> Loss | AA9: =ROUND((C9-B9)*1440,1) -> 26.9 | AB9: =IF(AA9<1,"a) <1 min",IF(AA9<10,"b) 1-10 min",IF(AA9<60,"c) 10-60 min",IF(AA9<240,"d) 1-4 h","e) 4 h+")))) -> c) 10-60 min | AC9: =IF(P9<10,"a) <10",IF(P9<20,"b) 10-20",IF(P9<40,"c) 20-40",IF(P9<80,"d) 40-80","e) 80+")))) -> d) 40-80 | AD9: =Summary!$C$5+SUM(X$2:X9) -> 99778.6 | AE9: =MAX(AE8,AD9) -> 100224.34 | AF9: =AE9-AD9 -> 445.74 | AG9: =IFERROR(AF9/AE9,0) -> 0.0044474227
A10: 9 | B10: 45029.072 | C10: 45029.084 | D10: =INT(C10) -> 45029 | E10: =D10-WEEKDAY(D10,3) -> 45026 | F10: 2023-04 | G10: 2023 | H10: Thu | I10: 1 | J10: SELL | K10: PDL breakout | L10: 0.35 | M10: 12826.8 | N10: 12831.31 | O10: 12817.77 | P10: =ABS(M10-N10) -> 4.51 | Q10: =IF(O10="","",ABS(O10-M10)) -> 9.03 | R10: =P10*L10*Summary!$C$6 -> 31.57 | S10: 12831.79 | T10: Initial stop loss | U10: =IF(J10="BUY",S10-M10,M10-S10) -> -4.99 | V10: 0 | W10: 0 | X10: -34.93 | Y10: =IFERROR(X10/R10,0) -> -1.1064302 | Z10: =IF(X10>0,"Win",IF(X10<0,"Loss","Flat")) -> Loss | AA10: =ROUND((C10-B10)*1440,1) -> 16.7 | AB10: =IF(AA10<1,"a) <1 min",IF(AA10<10,"b) 1-10 min",IF(AA10<60,"c) 10-60 min",IF(AA10<240,"d) 1-4 h","e) 4 h+")))) -> c) 10-60 min | AC10: =IF(P10<10,"a) <10",IF(P10<20,"b) 10-20",IF(P10<40,"c) 20-40",IF(P10<80,"d) 40-80","e) 80+")))) -> a) <10 | AD10: =Summary!$C$5+SUM(X$2:X10) -> 99743.67 | AE10: =MAX(AE9,AD10) -> 100224.34 | AF10: =AE10-AD10 -> 480.67 | AG10: =IFERROR(AF10/AE10,0) -> 0.0047959408
A11: 10 | B11: 45030.702 | C11: 45030.709 | D11: =INT(C11) -> 45030 | E11: =D11-WEEKDAY(D11,3) -> 45026 | F11: 2023-04 | G11: 2023 | H11: Fri | I11: 16 | J11: BUY | K11: PDH breakout | L11: 0.34 | M11: 13133.29 | N11: 13113.72 | O11: 13171.86 | P11: =ABS(M11-N11) -> 19.57 | Q11: =IF(O11="","",ABS(O11-M11)) -> 38.57 | R11: =P11*L11*Summary!$C$6 -> 133.076 | S11: 13112.82 | T11: Initial stop loss | U11: =IF(J11="BUY",S11-M11,M11-S11) -> -20.47 | V11: 0 | W11: 0 | X11: -139.2 | Y11: =IFERROR(X11/R11,0) -> -1.0460188 | Z11: =IF(X11>0,"Win",IF(X11<0,"Loss","Flat")) -> Loss | AA11: =ROUND((C11-B11)*1440,1) -> 9.7 | AB11: =IF(AA11<1,"a) <1 min",IF(AA11<10,"b) 1-10 min",IF(AA11<60,"c) 10-60 min",IF(AA11<240,"d) 1-4 h","e) 4 h+")))) -> b) 1-10 min | AC11: =IF(P11<10,"a) <10",IF(P11<20,"b) 10-20",IF(P11<40,"c) 20-40",IF(P11<80,"d) 40-80","e) 80+")))) -> b) 10-20 | AD11: =Summary!$C$5+SUM(X$2:X11) -> 99604.47 | AE11: =MAX(AE10,AD11) -> 100224.34 | AF11: =AE11-AD11 -> 619.87 | AG11: =IFERROR(AF11/AE11,0) -> 0.006184825
A12: 11 | B12: 45034.463 | C12: 45034.465 | D12: =INT(C12) -> 45034 | E12: =D12-WEEKDAY(D12,3) -> 45033 | F12: 2023-04 | G12: 2023 | H12: Tue | I12: 11 | J12: BUY | K12: PDH breakout | L12: 0.34 | M12: 13122.88 | N12: 13112.51 | O12: 13143.47 | P12: =ABS(M12-N12) -> 10.37 | Q12: =IF(O12="","",ABS(O12-M12)) -> 20.59 | R12: =P12*L12*Summary!$C$6 -> 70.516 | S12: 13112.36 | T12: Initial stop loss | U12: =IF(J12="BUY",S12-M12,M12-S12) -> -10.52 | V12: 0 | W12: 0 | X12: -71.54 | Y12: =IFERROR(X12/R12,0) -> -1.0145215 | Z12: =IF(X12>0,"Win",IF(X12<0,"Loss","Flat")) -> Loss | AA12: =ROUND((C12-B12)*1440,1) -> 2.1 | AB12: =IF(AA12<1,"a) <1 min",IF(AA12<10,"b) 1-10 min",IF(AA12<60,"c) 10-60 min",IF(AA12<240,"d) 1-4 h","e) 4 h+")))) -> b) 1-10 min | AC12: =IF(P12<10,"a) <10",IF(P12<20,"b) 10-20",IF(P12<40,"c) 20-40",IF(P12<80,"d) 40-80","e) 80+")))) -> b) 10-20 | AD12: =Summary!$C$5+SUM(X$2:X12) -> 99532.93 | AE12: =MAX(AE11,AD12) -> 100224.34 | AF12: =AE12-AD12 -> 691.41 | AG12: =IFERROR(AF12/AE12,0) -> 0.0068986236
A13: 12 | B13: 45035.384 | C13: 45035.392 | D13: =INT(C13) -> 45035 | E13: =D13-WEEKDAY(D13,3) -> 45033 | F13: 2023-04 | G13: 2023 | H13: Wed | I13: 9 | J13: SELL | K13: PDL breakout | L13: 0.34 | M13: 13039.78 | N13: 13048.7 | O13: 13021.8 | P13: =ABS(M13-N13) -> 8.92 | Q13: =IF(O13="","",ABS(O13-M13)) -> 17.98 | R13: =P13*L13*Summary!$C$6 -> 60.656 | S13: 13021.55 | T13: Take profit | U13: =IF(J13="BUY",S13-M13,M13-S13) -> 18.23 | V13: 0 | W13: 0 | X13: 123.96 | Y13: =IFERROR(X13/R13,0) -> 2.043656 | Z13: =IF(X13>0,"Win",IF(X13<0,"Loss","Flat")) -> Win | AA13: =ROUND((C13-B13)*1440,1) -> 11.6 | AB13: =IF(AA13<1,"a) <1 min",IF(AA13<10,"b) 1-10 min",IF(AA13<60,"c) 10-60 min",IF(AA13<240,"d) 1-4 h","e) 4 h+")))) -> c) 10-60 min | AC13: =IF(P13<10,"a) <10",IF(P13<20,"b) 10-20",IF(P13<40,"c) 20-40",IF(P13<80,"d) 40-80","e) 80+")))) -> a) <10 | AD13: =Summary!$C$5+SUM(X$2:X13) -> 99656.89 | AE13: =MAX(AE12,AD13) -> 100224.34 | AF13: =AE13-AD13 -> 567.45 | AG13: =IFERROR(AF13/AE13,0) -> 0.0056617983
A14: 13 | B14: 45036.447 | C14: 45036.489 | D14: =INT(C14) -> 45036 | E14: =D14-WEEKDAY(D14,3) -> 45033 | F14: 2023-04 | G14: 2023 | H14: Thu | I14: 10 | J14: SELL | K14: PDL breakout | L14: 0.34 | M14: 12964.08 | N14: 12976.42 | O14: 12939.25 | P14: =ABS(M14-N14) -> 12.34 | Q14: =IF(O14="","",ABS(O14-M14)) -> 24.83 | R14: =P14*L14*Summary!$C$6 -> 83.912 | S14: 12939.07 | T14: Take profit | U14: =IF(J14="BUY",S14-M14,M14-S14) -> 25.01 | V14: 0 | W14: 0 | X14: 170.07 | Y14: =IFERROR(X14/R14,0) -> 2.0267661 | Z14: =IF(X14>0,"Win",IF(X14<0,"Loss","Flat")) -> Win | AA14: =ROUND((C14-B14)*1440,1) -> 60.6 | AB14: =IF(AA14<1,"a) <1 min",IF(AA14<10,"b) 1-10 min",IF(AA14<60,"c) 10-60 min",IF(AA14<240,"d) 1-4 h","e) 4 h+")))) -> d) 1-4 h | AC14: =IF(P14<10,"a) <10",IF(P14<20,"b) 10-20",IF(P14<40,"c) 20-40",IF(P14<80,"d) 40-80","e) 80+")))) -> b) 10-20 | AD14: =Summary!$C$5+SUM(X$2:X14) -> 99826.96 | AE14: =MAX(AE13,AD14) -> 100224.34 | AF14: =AE14-AD14 -> 397.38 | AG14: =IFERROR(AF14/AE14,0) -> 0.0039649051
... A884: 883 | B884: 46290.355 | C884: 46290.362 | D884: =INT(C884) -> 46290 | E884: =D884-WEEKDAY(D884,3) -> 46286 | F884: 2026-09 | G884: 2026 | H884: Fri | I884: 8 | J884: BUY | K884: PDH breakout | L884: 0.17 | M884: 30537.4 | N884: 30521.1 | O884: 30570 | P884: =ABS(M884-N884) -> 16.3 | Q884: =IF(O884="","",ABS(O884-M884)) -> 32.6 | R884: =P884*L884*Summary!$C$6 -> 55.42 | S884: 30570.08 | T884: Take profit | U884: =IF(J884="BUY",S884-M884,M884-S884) -> 32.68 | V884: 0 | W884: 0 | X884: 111.11 | Y884: =IFERROR(X884/R884,0) -> 2.0048719 | Z884: =IF(X884>0,"Win",IF(X884<0,"Loss","Flat")) -> Win | AA884: =ROUND((C884-B884)*1440,1) -> 10 | AB884: =IF(AA884<1,"a) <1 min",IF(AA884<10,"b) 1-10 min",IF(AA884<60,"c) 10-60 min",IF(AA884<240,"d) 1-4 h","e) 4 h+")))) -> c) 10-60 min | AC884: =IF(P884<10,"a) <10",IF(P884<20,"b) 10-20",IF(P884<40,"c) 20-40",IF(P884<80,"d) 40-80","e) 80+")))) -> b) 10-20 | AD884: =Summary!$C$5+SUM(X$2:X884) -> 117717.69 | AE884: =MAX(AE883,AD884) -> 117717.69 | AF884: =AE884-AD884 -> 0 | AG884: =IFERROR(AF884/AE884,0) -> 0

Sheet Breakdown
A1: Where the money is made and lost
A3: By side | H3: Is one direction worse than the other?
A4: side | B4: Trades | C4: Win rate | D4: Net profit | E4: Avg per trade | F4: Avg R | G4: Profit factor
A5: BUY | B5: =COUNTIFS(Trades!$J$2:$J$884,$A5) -> 508 | C5: =IFERROR(COUNTIFS(Trades!$J$2:$J$884,$A5,Trades!$Z$2:$Z$884,"Win")/B5,0) -> 0.34251969 | D5: =SUMIFS(Trades!$X$2:$X$884,Trades!$J$2:$J$884,$A5) -> 9002.57 | E5: =IFERROR(D5/B5,0) -> 17.721594 | F5: =IFERROR(AVERAGEIFS(Trades!$Y$2:$Y$884,Trades!$J$2:$J$884,$A5),0) -> 0.23450852 | G5: =IFERROR(SUMIFS(Trades!$X$2:$X$884,Trades!$J$2:$J$884,$A5,Trades!$X$2:$X$884,">0")/-SUMIFS(Trades!$X$2:$X$884,Trades!$J$2:$J$884,$A5,Trades!$X$2:$X$884,"<0"),"-") -> 1.3684364
A6: SELL | B6: =COUNTIFS(Trades!$J$2:$J$884,$A6) -> 375 | C6: =IFERROR(COUNTIFS(Trades!$J$2:$J$884,$A6,Trades!$Z$2:$Z$884,"Win")/B6,0) -> 0.288 | D6: =SUMIFS(Trades!$X$2:$X$884,Trades!$J$2:$J$884,$A6) -> 8715.12 | E6: =IFERROR(D6/B6,0) -> 23.24032 | F6: =IFERROR(AVERAGEIFS(Trades!$Y$2:$Y$884,Trades!$J$2:$J$884,$A6),0) -> 0.15343764 | G6: =IFERROR(SUMIFS(Trades!$X$2:$X$884,Trades!$J$2:$J$884,$A6,Trades!$X$2:$X$884,">0")/-SUMIFS(Trades!$X$2:$X$884,Trades!$J$2:$J$884,$A6,Trades!$X$2:$X$884,"<0"),"-") -> 1.3928864
A7: Total | B7: =SUM(B5:B6) -> 883 | D7: =SUM(D5:D6) -> 17717.69
A9: By setup | H9: Entry comment written by the EA.
A10: setup | B10: Trades | C10: Win rate | D10: Net profit | E10: Avg per trade | F10: Avg R | G10: Profit factor
A11: PDH breakout | B11: =COUNTIFS(Trades!$K$2:$K$884,$A11) -> 508 | C11: =IFERROR(COUNTIFS(Trades!$K$2:$K$884,$A11,Trades!$Z$2:$Z$884,"Win")/B11,0) -> 0.34251969 | D11: =SUMIFS(Trades!$X$2:$X$884,Trades!$K$2:$K$884,$A11) -> 9002.57 | E11: =IFERROR(D11/B11,0) -> 17.721594 | F11: =IFERROR(AVERAGEIFS(Trades!$Y$2:$Y$884,Trades!$K$2:$K$884,$A11),0) -> 0.23450852 | G11: =IFERROR(SUMIFS(Trades!$X$2:$X$884,Trades!$K$2:$K$884,$A11,Trades!$X$2:$X$884,">0")/-SUMIFS(Trades!$X$2:$X$884,Trades!$K$2:$K$884,$A11,Trades!$X$2:$X$884,"<0"),"-") -> 1.3684364
A12: PDL breakout | B12: =COUNTIFS(Trades!$K$2:$K$884,$A12) -> 375 | C12: =IFERROR(COUNTIFS(Trades!$K$2:$K$884,$A12,Trades!$Z$2:$Z$884,"Win")/B12,0) -> 0.288 | D12: =SUMIFS(Trades!$X$2:$X$884,Trades!$K$2:$K$884,$A12) -> 8715.12 | E12: =IFERROR(D12/B12,0) -> 23.24032 | F12: =IFERROR(AVERAGEIFS(Trades!$Y$2:$Y$884,Trades!$K$2:$K$884,$A12),0) -> 0.15343764 | G12: =IFERROR(SUMIFS(Trades!$X$2:$X$884,Trades!$K$2:$K$884,$A12,Trades!$X$2:$X$884,">0")/-SUMIFS(Trades!$X$2:$X$884,Trades!$K$2:$K$884,$A12,Trades!$X$2:$X$884,"<0"),"-") -> 1.3928864
A13: Total | B13: =SUM(B11:B12) -> 883 | D13: =SUM(D11:D12) -> 17717.69
A15: By exit reason | H15: Breakeven stop = price reached the breakeven trigger, then came back to entry. Small losses there are slippage/commission.
A16: exit reason | B16: Trades | C16: Win rate | D16: Net profit | E16: Avg per trade | F16: Avg R | G16: Profit factor
A17: Take profit | B17: =COUNTIFS(Trades!$T$2:$T$884,$A17) -> 282 | C17: =IFERROR(COUNTIFS(Trades!$T$2:$T$884,$A17,Trades!$Z$2:$Z$884,"Win")/B17,0) -> 1 | D17: =SUMIFS(Trades!$X$2:$X$884,Trades!$T$2:$T$884,$A17) -> 64334.51 | E17: =IFERROR(D17/B17,0) -> 228.13656 | F17: =IFERROR(AVERAGEIFS(Trades!$Y$2:$Y$884,Trades!$T$2:$T$884,$A17),0) -> 2.0545413 | G17: =IFERROR(SUMIFS(Trades!$X$2:$X$884,Trades!$T$2:$T$884,$A17,Trades!$X$2:$X$884,">0")/-SUMIFS(Trades!$X$2:$X$884,Trades!$T$2:$T$884,$A17,Trades!$X$2:$X$884,"<0"),"-") -> -
A18: Initial stop loss | B18: =COUNTIFS(Trades!$T$2:$T$884,$A18) -> 386 | C18: =IFERROR(COUNTIFS(Trades!$T$2:$T$884,$A18,Trades!$Z$2:$Z$884,"Win")/B18,0) -> 0 | D18: =SUMIFS(Trades!$X$2:$X$884,Trades!$T$2:$T$884,$A18) -> -45672.71 | E18: =IFERROR(D18/B18,0) -> -118.32308 | F18: =IFERROR(AVERAGEIFS(Trades!$Y$2:$Y$884,Trades!$T$2:$T$884,$A18),0) -> -1.0260953 | G18: =IFERROR(SUMIFS(Trades!$X$2:$X$884,Trades!$T$2:$T$884,$A18,Trades!$X$2:$X$884,">0")/-SUMIFS(Trades!$X$2:$X$884,Trades!$T$2:$T$884,$A18,Trades!$X$2:$X$884,"<0"),"-") -> 0
A19: Breakeven stop | B19: =COUNTIFS(Trades!$T$2:$T$884,$A19) -> 215 | C19: =IFERROR(COUNTIFS(Trades!$T$2:$T$884,$A19,Trades!$Z$2:$Z$884,"Win")/B19,0) -> 0 | D19: =SUMIFS(Trades!$X$2:$X$884,Trades!$T$2:$T$884,$A19) -> -944.11 | E19: =IFERROR(D19/B19,0) -> -4.3912093 | F19: =IFERROR(AVERAGEIFS(Trades!$Y$2:$Y$884,Trades!$T$2:$T$884,$A19),0) -> -0.030876279 | G19: =IFERROR(SUMIFS(Trades!$X$2:$X$884,Trades!$T$2:$T$884,$A19,Trades!$X$2:$X$884,">0")/-SUMIFS(Trades!$X$2:$X$884,Trades!$T$2:$T$884,$A19,Trades!$X$2:$X$884,"<0"),"-") -> 0
A20: Moved stop (loss side) | B20: =COUNTIFS(Trades!$T$2:$T$884,$A20) -> 0 | C20: =IFERROR(COUNTIFS(Trades!$T$2:$T$884,$A20,Trades!$Z$2:$Z$884,"Win")/B20,0) -> 0 | D20: =SUMIFS(Trades!$X$2:$X$884,Trades!$T$2:$T$884,$A20) -> 0 | E20: =IFERROR(D20/B20,0) -> 0 | F20: =IFERROR(AVERAGEIFS(Trades!$Y$2:$Y$884,Trades!$T$2:$T$884,$A20),0) -> 0 | G20: =IFERROR(SUMIFS(Trades!$X$2:$X$884,Trades!$T$2:$T$884,$A20,Trades!$X$2:$X$884,">0")/-SUMIFS(Trades!$X$2:$X$884,Trades!$T$2:$T$884,$A20,Trades!$X$2:$X$884,"<0"),"-") -> -
A21: Closed by EA | B21: =COUNTIFS(Trades!$T$2:$T$884,$A21) -> 0 | C21: =IFERROR(COUNTIFS(Trades!$T$2:$T$884,$A21,Trades!$Z$2:$Z$884,"Win")/B21,0) -> 0 | D21: =SUMIFS(Trades!$X$2:$X$884,Trades!$T$2:$T$884,$A21) -> 0 | E21: =IFERROR(D21/B21,0) -> 0 | F21: =IFERROR(AVERAGEIFS(Trades!$Y$2:$Y$884,Trades!$T$2:$T$884,$A21),0) -> 0 | G21: =IFERROR(SUMIFS(Trades!$X$2:$X$884,Trades!$T$2:$T$884,$A21,Trades!$X$2:$X$884,">0")/-SUMIFS(Trades!$X$2:$X$884,Trades!$T$2:$T$884,$A21,Trades!$X$2:$X$884,"<0"),"-") -> -
A22: Total | B22: =SUM(B17:B21) -> 883 | D22: =SUM(D17:D21) -> 17717.69
A24: By weekday (entry) | H24: Day of the week the trade was entered (server time).
A25: weekday (entry) | B25: Trades | C25: Win rate | D25: Net profit | E25: Avg per trade | F25: Avg R | G25: Profit factor
A26: Mon | B26: =COUNTIFS(Trades!$H$2:$H$884,$A26) -> 165 | C26: =IFERROR(COUNTIFS(Trades!$H$2:$H$884,$A26,Trades!$Z$2:$Z$884,"Win")/B26,0) -> 0.32121212 | D26: =SUMIFS(Trades!$X$2:$X$884,Trades!$H$2:$H$884,$A26) -> 3816.28 | E26: =IFERROR(D26/B26,0) -> 23.12897 | F26: =IFERROR(AVERAGEIFS(Trades!$Y$2:$Y$884,Trades!$H$2:$H$884,$A26),0) -> 0.17139064 | G26: =IFERROR(SUMIFS(Trades!$X$2:$X$884,Trades!$H$2:$H$884,$A26,Trades!$X$2:$X$884,">0")/-SUMIFS(Trades!$X$2:$X$884,Trades!$H$2:$H$884,$A26,Trades!$X$2:$X$884,"<0"),"-") -> 1.3713136
A27: Tue | B27: =COUNTIFS(Trades!$H$2:$H$884,$A27) -> 179 | C27: =IFERROR(COUNTIFS(Trades!$H$2:$H$884,$A27,Trades!$Z$2:$Z$884,"Win")/B27,0) -> 0.29608939 | D27: =SUMIFS(Trades!$X$2:$X$884,Trades!$H$2:$H$884,$A27) -> -860.87 | E27: =IFERROR(D27/B27,0) -> -4.8093296 | F27: =IFERROR(AVERAGEIFS(Trades!$Y$2:$Y$884,Trades!$H$2:$H$884,$A27),0) -> 0.13893481 | G27: =IFERROR(SUMIFS(Trades!$X$2:$X$884,Trades!$H$2:$H$884,$A27,Trades!$X$2:$X$884,">0")/-SUMIFS(Trades!$X$2:$X$884,Trades!$H$2:$H$884,$A27,Trades!$X$2:$X$884,"<0"),"-") -> 0.90514341
A28: Wed | B28: =COUNTIFS(Trades!$H$2:$H$884,$A28) -> 187 | C28: =IFERROR(COUNTIFS(Trades!$H$2:$H$884,$A28,Trades!$Z$2:$Z$884,"Win")/B28,0) -> 0.29946524 | D28: =SUMIFS(Trades!$X$2:$X$884,Trades!$H$2:$H$884,$A28) -> 4652.11 | E28: =IFERROR(D28/B28,0) -> 24.877594 | F28: =IFERROR(AVERAGEIFS(Trades!$Y$2:$Y$884,Trades!$H$2:$H$884,$A28),0) -> 0.14474824 | G28: =IFERROR(SUMIFS(Trades!$X$2:$X$884,Trades!$H$2:$H$884,$A28,Trades!$X$2:$X$884,">0")/-SUMIFS(Trades!$X$2:$X$884,Trades!$H$2:$H$884,$A28,Trades!$X$2:$X$884,"<0"),"-") -> 1.4428902
A29: Thu | B29: =COUNTIFS(Trades!$H$2:$H$884,$A29) -> 187 | C29: =IFERROR(COUNTIFS(Trades!$H$2:$H$884,$A29,Trades!$Z$2:$Z$884,"Win")/B29,0) -> 0.34759358 | D29: =SUMIFS(Trades!$X$2:$X$884,Trades!$H$2:$H$884,$A29) -> 6869.27 | E29: =IFERROR(D29/B29,0) -> 36.734064 | F29: =IFERROR(AVERAGEIFS(Trades!$Y$2:$Y$884,Trades!$H$2:$H$884,$A29),0) -> 0.30272865 | G29: =IFERROR(SUMIFS(Trades!$X$2:$X$884,Trades!$H$2:$H$884,$A29,Trades!$X$2:$X$884,">0")/-SUMIFS(Trades!$X$2:$X$884,Trades!$H$2:$H$884,$A29,Trades!$X$2:$X$884,"<0"),"-") -> 1.7385788
A30: Fri | B30: =COUNTIFS(Trades!$H$2:$H$884,$A30) -> 165 | C30: =IFERROR(COUNTIFS(Trades!$H$2:$H$884,$A30,Trades!$Z$2:$Z$884,"Win")/B30,0) -> 0.33333333 | D30: =SUMIFS(Trades!$X$2:$X$884,Trades!$H$2:$H$884,$A30) -> 3240.9 | E30: =IFERROR(D30/B30,0) -> 19.641818 | F30: =IFERROR(AVERAGEIFS(Trades!$Y$2:$Y$884,Trades!$H$2:$H$884,$A30),0) -> 0.24146957 | G30: =IFERROR(SUMIFS(Trades!$X$2:$X$884,Trades!$H$2:$H$884,$A30,Trades!$X$2:$X$884,">0")/-SUMIFS(Trades!$X$2:$X$884,Trades!$H$2:$H$884,$A30,Trades!$X$2:$X$884,"<0"),"-") -> 1.4345005
A31: Total | B31: =SUM(B26:B30) -> 883 | D31: =SUM(D26:D30) -> 17717.69
A33: By entry hour (server) | H33: Server hour of entry. Hours with a clearly negative total are candidates for a no-trade window.
A34: entry hour (server) | B34: Trades | C34: Win rate | D34: Net profit | E34: Avg per trade | F34: Avg R | G34: Profit factor
A35: 1 | B35: =COUNTIFS(Trades!$I$2:$I$884,$A35) -> 176 | C35: =IFERROR(COUNTIFS(Trades!$I$2:$I$884,$A35,Trades!$Z$2:$Z$884,"Win")/B35,0) -> 0.39772727 | D35: =SUMIFS(Trades!$X$2:$X$884,Trades!$I$2:$I$884,$A35) -> 10454.29 | E35: =IFERROR(D35/B35,0) -> 59.399375 | F35: =IFERROR(AVERAGEIFS(Trades!$Y$2:$Y$884,Trades!$I$2:$I$884,$A35),0) -> 0.39008615 | G35: =IFERROR(SUMIFS(Trades!$X$2:$X$884,Trades!$I$2:$I$884,$A35,Trades!$X$2:$X$884,">0")/-SUMIFS(Trades!$X$2:$X$884,Trades!$I$2:$I$884,$A35,Trades!$X$2:$X$884,"<0"),"-") -> 1.9849408
A36: 2 | B36: =COUNTIFS(Trades!$I$2:$I$884,$A36) -> 52 | C36: =IFERROR(COUNTIFS(Trades!$I$2:$I$884,$A36,Trades!$Z$2:$Z$884,"Win")/B36,0) -> 0.17307692 | D36: =SUMIFS(Trades!$X$2:$X$884,Trades!$I$2:$I$884,$A36) -> -834.04 | E36: =IFERROR(D36/B36,0) -> -16.039231 | F36: =IFERROR(AVERAGEIFS(Trades!$Y$2:$Y$884,Trades!$I$2:$I$884,$A36),0) -> -0.19347545 | G36: =IFERROR(SUMIFS(Trades!$X$2:$X$884,Trades!$I$2:$I$884,$A36,Trades!$X$2:$X$884,">0")/-SUMIFS(Trades!$X$2:$X$884,Trades!$I$2:$I$884,$A36,Trades!$X$2:$X$884,"<0"),"-") -> 0.46461768
A37: 3 | B37: =COUNTIFS(Trades!$I$2:$I$884,$A37) -> 45 | C37: =IFERROR(COUNTIFS(Trades!$I$2:$I$884,$A37,Trades!$Z$2:$Z$884,"Win")/B37,0) -> 0.35555556 | D37: =SUMIFS(Trades!$X$2:$X$884,Trades!$I$2:$I$884,$A37) -> 402.56 | E37: =IFERROR(D37/B37,0) -> 8.9457778 | F37: =IFERROR(AVERAGEIFS(Trades!$Y$2:$Y$884,Trades!$I$2:$I$884,$A37),0) -> 0.3420956 | G37: =IFERROR(SUMIFS(Trades!$X$2:$X$884,Trades!$I$2:$I$884,$A37,Trades!$X$2:$X$884,">0")/-SUMIFS(Trades!$X$2:$X$884,Trades!$I$2:$I$884,$A37,Trades!$X$2:$X$884,"<0"),"-") -> 1.2586681
A38: 4 | B38: =COUNTIFS(Trades!$I$2:$I$884,$A38) -> 26 | C38: =IFERROR(COUNTIFS(Trades!$I$2:$I$884,$A38,Trades!$Z$2:$Z$884,"Win")/B38,0) -> 0.34615385 | D38: =SUMIFS(Trades!$X$2:$X$884,Trades!$I$2:$I$884,$A38) -> 322.25 | E38: =IFERROR(D38/B38,0) -> 12.394231 | F38: =IFERROR(AVERAGEIFS(Trades!$Y$2:$Y$884,Trades!$I$2:$I$884,$A38),0) -> 0.29922405 | G38: =IFERROR(SUMIFS(Trades!$X$2:$X$884,Trades!$I$2:$I$884,$A38,Trades!$X$2:$X$884,">0")/-SUMIFS(Trades!$X$2:$X$884,Trades!$I$2:$I$884,$A38,Trades!$X$2:$X$884,"<0"),"-") -> 1.4740365
A39: 5 | B39: =COUNTIFS(Trades!$I$2:$I$884,$A39) -> 25 | C39: =IFERROR(COUNTIFS(Trades!$I$2:$I$884,$A39,Trades!$Z$2:$Z$884,"Win")/B39,0) -> 0.2 | D39: =SUMIFS(Trades!$X$2:$X$884,Trades!$I$2:$I$884,$A39) -> 345.75 | E39: =IFERROR(D39/B39,0) -> 13.83 | F39: =IFERROR(AVERAGEIFS(Trades!$Y$2:$Y$884,Trades!$I$2:$I$884,$A39),0) -> -0.17965576 | G39: =IFERROR(SUMIFS(Trades!$X$2:$X$884,Trades!$I$2:$I$884,$A39,Trades!$X$2:$X$884,">0")/-SUMIFS(Trades!$X$2:$X$884,Trades!$I$2:$I$884,$A39,Trades!$X$2:$X$884,"<0"),"-") -> 1.467881
A40: 6 | B40: =COUNTIFS(Trades!$I$2:$I$884,$A40) -> 15 | C40: =IFERROR(COUNTIFS(Trades!$I$2:$I$884,$A40,Trades!$Z$2:$Z$884,"Win")/B40,0) -> 0.33333333 | D40: =SUMIFS(Trades!$X$2:$X$884,Trades!$I$2:$I$884,$A40) -> 193.47 | E40: =IFERROR(D40/B40,0) -> 12.898 | F40: =IFERROR(AVERAGEIFS(Trades!$Y$2:$Y$884,Trades!$I$2:$I$884,$A40),0) -> 0.084281367 | G40: =IFERROR(SUMIFS(Trades!$X$2:$X$884,Trades!$I$2:$I$884,$A40,Trades!$X$2:$X$884,">0")/-SUMIFS(Trades!$X$2:$X$884,Trades!$I$2:$I$884,$A40,Trades!$X$2:$X$884,"<0"),"-") -> 1.4068085
A41: 7 | B41: =COUNTIFS(Trades!$I$2:$I$884,$A41) -> 12 | C41: =IFERROR(COUNTIFS(Trades!$I$2:$I$884,$A41,Trades!$Z$2:$Z$884,"Win")/B41,0) -> 0.33333333 | D41: =SUMIFS(Trades!$X$2:$X$884,Trades!$I$2:$I$884,$A41) -> 47.86 | E41: =IFERROR(D41/B41,0) -> 3.9883333 | F41: =IFERROR(AVERAGEIFS(Trades!$Y$2:$Y$884,Trades!$I$2:$I$884,$A41),0) -> 0.34407342 | G41: =IFERROR(SUMIFS(Trades!$X$2:$X$884,Trades!$I$2:$I$884,$A41,Trades!$X$2:$X$884,">0")/-SUMIFS(Trades!$X$2:$X$884,Trades!$I$2:$I$884,$A41,Trades!$X$2:$X$884,"<0"),"-") -> 1.2071772
A42: 8 | B42: =COUNTIFS(Trades!$I$2:$I$884,$A42) -> 19 | C42: =IFERROR(COUNTIFS(Trades!$I$2:$I$884,$A42,Trades!$Z$2:$Z$884,"Win")/B42,0) -> 0.52631579 | D42: =SUMIFS(Trades!$X$2:$X$884,Trades!$I$2:$I$884,$A42) -> 734.06 | E42: =IFERROR(D42/B42,0) -> 38.634737 | F42: =IFERROR(AVERAGEIFS(Trades!$Y$2:$Y$884,Trades!$I$2:$I$884,$A42),0) -> 0.75501222 | G42: =IFERROR(SUMIFS(Trades!$X$2:$X$884,Trades!$I$2:$I$884,$A42,Trades!$X$2:$X$884,">0")/-SUMIFS(Trades!$X$2:$X$884,Trades!$I$2:$I$884,$A42,Trades!$X$2:$X$884,"<0"),"-") -> 3.9039481
A43: 9 | B43: =COUNTIFS(Trades!$I$2:$I$884,$A43) -> 27 | C43: =IFERROR(COUNTIFS(Trades!$I$2:$I$884,$A43,Trades!$Z$2:$Z$884,"Win")/B43,0) -> 0.44444444 | D43: =SUMIFS(Trades!$X$2:$X$884,Trades!$I$2:$I$884,$A43) -> 724.02 | E43: =IFERROR(D43/B43,0) -> 26.815556 | F43: =IFERROR(AVERAGEIFS(Trades!$Y$2:$Y$884,Trades!$I$2:$I$884,$A43),0) -> 0.64417786 | G43: =IFERROR(SUMIFS(Trades!$X$2:$X$884,Trades!$I$2:$I$884,$A43,Trades!$X$2:$X$884,">0")/-SUMIFS(Trades!$X$2:$X$884,Trades!$I$2:$I$884,$A43,Trades!$X$2:$X$884,"<0"),"-") -> 2.3247338
A44: 10 | B44: =COUNTIFS(Trades!$I$2:$I$884,$A44) -> 36 | C44: =IFERROR(COUNTIFS(Trades!$I$2:$I$884,$A44,Trades!$Z$2:$Z$884,"Win")/B44,0) -> 0.30555556 | D44: =SUMIFS(Trades!$X$2:$X$884,Trades!$I$2:$I$884,$A44) -> 578.49 | E44: =IFERROR(D44/B44,0) -> 16.069167 | F44: =IFERROR(AVERAGEIFS(Trades!$Y$2:$Y$884,Trades!$I$2:$I$884,$A44),0) -> 0.12759555 | G44: =IFERROR(SUMIFS(Trades!$X$2:$X$884,Trades!$I$2:$I$884,$A44,Trades!$X$2:$X$884,">0")/-SUMIFS(Trades!$X$2:$X$884,Trades!$I$2:$I$884,$A44,Trades!$X$2:$X$884,"<0"),"-") -> 1.51116
A45: 11 | B45: =COUNTIFS(Trades!$I$2:$I$884,$A45) -> 34 | C45: =IFERROR(COUNTIFS(Trades!$I$2:$I$884,$A45,Trades!$Z$2:$Z$884,"Win")/B45,0) -> 0.20588235 | D45: =SUMIFS(Trades!$X$2:$X$884,Trades!$I$2:$I$884,$A45) -> 320.63 | E45: =IFERROR(D45/B45,0) -> 9.4302941 | F45: =IFERROR(AVERAGEIFS(Trades!$Y$2:$Y$884,Trades!$I$2:$I$884,$A45),0) -> -0.078412338 | G45: =IFERROR(SUMIFS(Trades!$X$2:$X$884,Trades!$I$2:$I$884,$A45,Trades!$X$2:$X$884,">0")/-SUMIFS(Trades!$X$2:$X$884,Trades!$I$2:$I$884,$A45,Trades!$X$2:$X$884,"<0"),"-") -> 1.3012421
A46: 12 | B46: =COUNTIFS(Trades!$I$2:$I$884,$A46) -> 15 | C46: =IFERROR(COUNTIFS(Trades!$I$2:$I$884,$A46,Trades!$Z$2:$Z$884,"Win")/B46,0) -> 0.53333333 | D46: =SUMIFS(Trades!$X$2:$X$884,Trades!$I$2:$I$884,$A46) -> 785.44 | E46: =IFERROR(D46/B46,0) -> 52.362667 | F46: =IFERROR(AVERAGEIFS(Trades!$Y$2:$Y$884,Trades!$I$2:$I$884,$A46),0) -> 0.93430094 | G46: =IFERROR(SUMIFS(Trades!$X$2:$X$884,Trades!$I$2:$I$884,$A46,Trades!$X$2:$X$884,">0")/-SUMIFS(Trades!$X$2:$X$884,Trades!$I$2:$I$884,$A46,Trades!$X$2:$X$884,"<0"),"-") -> 4.4265771
... A57: 23 | B57: =COUNTIFS(Trades!$I$2:$I$884,$A57) -> 9 | C57: =IFERROR(COUNTIFS(Trades!$I$2:$I$884,$A57,Trades!$Z$2:$Z$884,"Win")/B57,0) -> 0.44444444 | D57: =SUMIFS(Trades!$X$2:$X$884,Trades!$I$2:$I$884,$A57) -> 244.93 | E57: =IFERROR(D57/B57,0) -> 27.214444 | F57: =IFERROR(AVERAGEIFS(Trades!$Y$2:$Y$884,Trades!$I$2:$I$884,$A57),0) -> 0.2763515 | G57: =IFERROR(SUMIFS(Trades!$X$2:$X$884,Trades!$I$2:$I$884,$A57,Trades!$X$2:$X$884,">0")/-SUMIFS(Trades!$X$2:$X$884,Trades!$I$2:$I$884,$A57,Trades!$X$2:$X$884,"<0"),"-") -> 1.2257399
A58: Total | B58: =SUM(B35:B57) -> 883 | D58: =SUM(D35:D57) -> 17717.69
A60: By hold time | H60: How long trades stayed open.
A61: hold time | B61: Trades | C61: Win rate | D61: Net profit | E61: Avg per trade | F61: Avg R | G61: Profit factor
A62: a) <1 min | B62: =COUNTIFS(Trades!$AB$2:$AB$884,$A62) -> 20 | C62: =IFERROR(COUNTIFS(Trades!$AB$2:$AB$884,$A62,Trades!$Z$2:$Z$884,"Win")/B62,0) -> 0.3 | D62: =SUMIFS(Trades!$X$2:$X$884,Trades!$AB$2:$AB$884,$A62) -> -768.22 | E62: =IFERROR(D62/B62,0) -> -38.411 | F62: =IFERROR(AVERAGEIFS(Trades!$Y$2:$Y$884,Trades!$AB$2:$AB$884,$A62),0) -> -0.1320171 | G62: =IFERROR(SUMIFS(Trades!$X$2:$X$884,Trades!$AB$2:$AB$884,$A62,Trades!$X$2:$X$884,">0")/-SUMIFS(Trades!$X$2:$X$884,Trades!$AB$2:$AB$884,$A62,Trades!$X$2:$X$884,"<0"),"-") -> 0.51907499
A63: b) 1-10 min | B63: =COUNTIFS(Trades!$AB$2:$AB$884,$A63) -> 381 | C63: =IFERROR(COUNTIFS(Trades!$AB$2:$AB$884,$A63,Trades!$Z$2:$Z$884,"Win")/B63,0) -> 0.26246719 | D63: =SUMIFS(Trades!$X$2:$X$884,Trades!$AB$2:$AB$884,$A63) -> -6020.47 | E63: =IFERROR(D63/B63,0) -> -15.801759 | F63: =IFERROR(AVERAGEIFS(Trades!$Y$2:$Y$884,Trades!$AB$2:$AB$884,$A63),0) -> -0.045297277 | G63: =IFERROR(SUMIFS(Trades!$X$2:$X$884,Trades!$AB$2:$AB$884,$A63,Trades!$X$2:$X$884,">0")/-SUMIFS(Trades!$X$2:$X$884,Trades!$AB$2:$AB$884,$A63,Trades!$X$2:$X$884,"<0"),"-") -> 0.73753921
A64: c) 10-60 min | B64: =COUNTIFS(Trades!$AB$2:$AB$884,$A64) -> 388 | C64: =IFERROR(COUNTIFS(Trades!$AB$2:$AB$884,$A64,Trades!$Z$2:$Z$884,"Win")/B64,0) -> 0.31958763 | D64: =SUMIFS(Trades!$X$2:$X$884,Trades!$AB$2:$AB$884,$A64) -> 6317.53 | E64: =IFERROR(D64/B64,0) -> 16.282294 | F64: =IFERROR(AVERAGEIFS(Trades!$Y$2:$Y$884,Trades!$AB$2:$AB$884,$A64),0) -> 0.28142406 | G64: =IFERROR(SUMIFS(Trades!$X$2:$X$884,Trades!$AB$2:$AB$884,$A64,Trades!$X$2:$X$884,">0")/-SUMIFS(Trades!$X$2:$X$884,Trades!$AB$2:$AB$884,$A64,Trades!$X$2:$X$884,"<0"),"-") -> 1.3395888
A65: d) 1-4 h | B65: =COUNTIFS(Trades!$AB$2:$AB$884,$A65) -> 64 | C65: =IFERROR(COUNTIFS(Trades!$AB$2:$AB$884,$A65,Trades!$Z$2:$Z$884,"Win")/B65,0) -> 0.484375 | D65: =SUMIFS(Trades!$X$2:$X$884,Trades!$AB$2:$AB$884,$A65) -> 8738.45 | E65: =IFERROR(D65/B65,0) -> 136.53828 | F65: =IFERROR(AVERAGEIFS(Trades!$Y$2:$Y$884,Trades!$AB$2:$AB$884,$A65),0) -> 0.78258705 | G65: =IFERROR(SUMIFS(Trades!$X$2:$X$884,Trades!$AB$2:$AB$884,$A65,Trades!$X$2:$X$884,">0")/-SUMIFS(Trades!$X$2:$X$884,Trades!$AB$2:$AB$884,$A65,Trades!$X$2:$X$884,"<0"),"-") -> 4.4879298
A66: e) 4 h+ | B66: =COUNTIFS(Trades!$AB$2:$AB$884,$A66) -> 30 | C66: =IFERROR(COUNTIFS(Trades!$AB$2:$AB$884,$A66,Trades!$Z$2:$Z$884,"Win")/B66,0) -> 0.7 | D66: =SUMIFS(Trades!$X$2:$X$884,Trades!$AB$2:$AB$884,$A66) -> 9450.4 | E66: =IFERROR(D66/B66,0) -> 315.01333 | F66: =IFERROR(AVERAGEIFS(Trades!$Y$2:$Y$884,Trades!$AB$2:$AB$884,$A66),0) -> 1.242998 | G66: =IFERROR(SUMIFS(Trades!$X$2:$X$884,Trades!$AB$2:$AB$884,$A66,Trades!$X$2:$X$884,">0")/-SUMIFS(Trades!$X$2:$X$884,Trades!$AB$2:$AB$884,$A66,Trades!$X$2:$X$884,"<0"),"-") -> 10.721834
A67: Total | B67: =SUM(B62:B66) -> 883 | D67: =SUM(D62:D66) -> 17717.69
A69: By SL distance (points) | H69: ATR-based stops: very small stops are easily hit by noise, very large ones mean volatile days.
A70: SL distance (points) | B70: Trades | C70: Win rate | D70: Net profit | E70: Avg per trade | F70: Avg R | G70: Profit factor
A71: a) <10 | B71: =COUNTIFS(Trades!$AC$2:$AC$884,$A71) -> 196 | C71: =IFERROR(COUNTIFS(Trades!$AC$2:$AC$884,$A71,Trades!$Z$2:$Z$884,"Win")/B71,0) -> 0.30612245 | D71: =SUMIFS(Trades!$X$2:$X$884,Trades!$AC$2:$AC$884,$A71) -> 929.14 | E71: =IFERROR(D71/B71,0) -> 4.7405102 | F71: =IFERROR(AVERAGEIFS(Trades!$Y$2:$Y$884,Trades!$AC$2:$AC$884,$A71),0) -> 0.16360065 | G71: =IFERROR(SUMIFS(Trades!$X$2:$X$884,Trades!$AC$2:$AC$884,$A71,Trades!$X$2:$X$884,">0")/-SUMIFS(Trades!$X$2:$X$884,Trades!$AC$2:$AC$884,$A71,Trades!$X$2:$X$884,"<0"),"-") -> 1.2662529
A72: b) 10-20 | B72: =COUNTIFS(Trades!$AC$2:$AC$884,$A72) -> 260 | C72: =IFERROR(COUNTIFS(Trades!$AC$2:$AC$884,$A72,Trades!$Z$2:$Z$884,"Win")/B72,0) -> 0.36923077 | D72: =SUMIFS(Trades!$X$2:$X$884,Trades!$AC$2:$AC$884,$A72) -> 5646.29 | E72: =IFERROR(D72/B72,0) -> 21.7165 | F72: =IFERROR(AVERAGEIFS(Trades!$Y$2:$Y$884,Trades!$AC$2:$AC$884,$A72),0) -> 0.33882459 | G72: =IFERROR(SUMIFS(Trades!$X$2:$X$884,Trades!$AC$2:$AC$884,$A72,Trades!$X$2:$X$884,">0")/-SUMIFS(Trades!$X$2:$X$884,Trades!$AC$2:$AC$884,$A72,Trades!$X$2:$X$884,"<0"),"-") -> 1.7433486
A73: c) 20-40 | B73: =COUNTIFS(Trades!$AC$2:$AC$884,$A73) -> 278 | C73: =IFERROR(COUNTIFS(Trades!$AC$2:$AC$884,$A73,Trades!$Z$2:$Z$884,"Win")/B73,0) -> 0.29136691 | D73: =SUMIFS(Trades!$X$2:$X$884,Trades!$AC$2:$AC$884,$A73) -> 5133.07 | E73: =IFERROR(D73/B73,0) -> 18.464281 | F73: =IFERROR(AVERAGEIFS(Trades!$Y$2:$Y$884,Trades!$AC$2:$AC$884,$A73),0) -> 0.12179163 | G73: =IFERROR(SUMIFS(Trades!$X$2:$X$884,Trades!$AC$2:$AC$884,$A73,Trades!$X$2:$X$884,">0")/-SUMIFS(Trades!$X$2:$X$884,Trades!$AC$2:$AC$884,$A73,Trades!$X$2:$X$884,"<0"),"-") -> 1.2974789
A74: d) 40-80 | B74: =COUNTIFS(Trades!$AC$2:$AC$884,$A74) -> 128 | C74: =IFERROR(COUNTIFS(Trades!$AC$2:$AC$884,$A74,Trades!$Z$2:$Z$884,"Win")/B74,0) -> 0.2890625 | D74: =SUMIFS(Trades!$X$2:$X$884,Trades!$AC$2:$AC$884,$A74) -> 3503.72 | E74: =IFERROR(D74/B74,0) -> 27.372812 | F74: =IFERROR(AVERAGEIFS(Trades!$Y$2:$Y$884,Trades!$AC$2:$AC$884,$A74),0) -> 0.12434493 | G74: =IFERROR(SUMIFS(Trades!$X$2:$X$884,Trades!$AC$2:$AC$884,$A74,Trades!$X$2:$X$884,">0")/-SUMIFS(Trades!$X$2:$X$884,Trades!$AC$2:$AC$884,$A74,Trades!$X$2:$X$884,"<0"),"-") -> 1.2403674
A75: e) 80+ | B75: =COUNTIFS(Trades!$AC$2:$AC$884,$A75) -> 21 | C75: =IFERROR(COUNTIFS(Trades!$AC$2:$AC$884,$A75,Trades!$Z$2:$Z$884,"Win")/B75,0) -> 0.38095238 | D75: =SUMIFS(Trades!$X$2:$X$884,Trades!$AC$2:$AC$884,$A75) -> 2505.47 | E75: =IFERROR(D75/B75,0) -> 119.3081 | F75: =IFERROR(AVERAGEIFS(Trades!$Y$2:$Y$884,Trades!$AC$2:$AC$884,$A75),0) -> 0.32071896 | G75: =IFERROR(SUMIFS(Trades!$X$2:$X$884,Trades!$AC$2:$AC$884,$A75,Trades!$X$2:$X$884,">0")/-SUMIFS(Trades!$X$2:$X$884,Trades!$AC$2:$AC$884,$A75,Trades!$X$2:$X$884,"<0"),"-") -> 1.6772236
A76: Total | B76: =SUM(B71:B75) -> 883 | D76: =SUM(D71:D75) -> 17717.69
A78: By year | H78: Same as the Yearly sheet, for side-by-side reading.
A79: year | B79: Trades | C79: Win rate | D79: Net profit | E79: Avg per trade | F79: Avg R | G79: Profit factor
A80: 2023 | B80: =COUNTIFS(Trades!$G$2:$G$884,$A80) -> 194 | C80: =IFERROR(COUNTIFS(Trades!$G$2:$G$884,$A80,Trades!$Z$2:$Z$884,"Win")/B80,0) -> 0.33505155 | D80: =SUMIFS(Trades!$X$2:$X$884,Trades!$G$2:$G$884,$A80) -> 4466.65 | E80: =IFERROR(D80/B80,0) -> 23.023969 | F80: =IFERROR(AVERAGEIFS(Trades!$Y$2:$Y$884,Trades!$G$2:$G$884,$A80),0) -> 0.20231396 | G80: =IFERROR(SUMIFS(Trades!$X$2:$X$884,Trades!$G$2:$G$884,$A80,Trades!$X$2:$X$884,">0")/-SUMIFS(Trades!$X$2:$X$884,Trades!$G$2:$G$884,$A80,Trades!$X$2:$X$884,"<0"),"-") -> 1.5297663
A81: 2024 | B81: =COUNTIFS(Trades!$G$2:$G$884,$A81) -> 244 | C81: =IFERROR(COUNTIFS(Trades!$G$2:$G$884,$A81,Trades!$Z$2:$Z$884,"Win")/B81,0) -> 0.29918033 | D81: =SUMIFS(Trades!$X$2:$X$884,Trades!$G$2:$G$884,$A81) -> 2375.02 | E81: =IFERROR(D81/B81,0) -> 9.7336885 | F81: =IFERROR(AVERAGEIFS(Trades!$Y$2:$Y$884,Trades!$G$2:$G$884,$A81),0) -> 0.1738651 | G81: =IFERROR(SUMIFS(Trades!$X$2:$X$884,Trades!$G$2:$G$884,$A81,Trades!$X$2:$X$884,">0")/-SUMIFS(Trades!$X$2:$X$884,Trades!$G$2:$G$884,$A81,Trades!$X$2:$X$884,"<0"),"-") -> 1.2109108
A82: 2025 | B82: =COUNTIFS(Trades!$G$2:$G$884,$A82) -> 257 | C82: =IFERROR(COUNTIFS(Trades!$G$2:$G$884,$A82,Trades!$Z$2:$Z$884,"Win")/B82,0) -> 0.32684825 | D82: =SUMIFS(Trades!$X$2:$X$884,Trades!$G$2:$G$884,$A82) -> 7225.36 | E82: =IFERROR(D82/B82,0) -> 28.114241 | F82: =IFERROR(AVERAGEIFS(Trades!$Y$2:$Y$884,Trades!$G$2:$G$884,$A82),0) -> 0.20520904 | G82: =IFERROR(SUMIFS(Trades!$X$2:$X$884,Trades!$G$2:$G$884,$A82,Trades!$X$2:$X$884,">0")/-SUMIFS(Trades!$X$2:$X$884,Trades!$G$2:$G$884,$A82,Trades!$X$2:$X$884,"<0"),"-") -> 1.4800766
A83: 2026 | B83: =COUNTIFS(Trades!$G$2:$G$884,$A83) -> 188 | C83: =IFERROR(COUNTIFS(Trades!$G$2:$G$884,$A83,Trades!$Z$2:$Z$884,"Win")/B83,0) -> 0.31914894 | D83: =SUMIFS(Trades!$X$2:$X$884,Trades!$G$2:$G$884,$A83) -> 3650.66 | E83: =IFERROR(D83/B83,0) -> 19.418404 | F83: =IFERROR(AVERAGEIFS(Trades!$Y$2:$Y$884,Trades!$G$2:$G$884,$A83),0) -> 0.22478047 | G83: =IFERROR(SUMIFS(Trades!$X$2:$X$884,Trades!$G$2:$G$884,$A83,Trades!$X$2:$X$884,">0")/-SUMIFS(Trades!$X$2:$X$884,Trades!$G$2:$G$884,$A83,Trades!$X$2:$X$884,"<0"),"-") -> 1.3074434
A84: Total | B84: =SUM(B80:B83) -> 883 | D84: =SUM(D80:D83) -> 17717.69
A86: R distribution | H86: How many trades ended in each R range.
A87: R range | B87: Trades | C87: Share | D87: Net profit
A88: worse than -1.05R | B88: =COUNTIFS(Trades!$Y$2:$Y$884,">=-99",Trades!$Y$2:$Y$884,"<-1.05") -> 53 | C88: =IFERROR(B88/Summary!$C$20,0) -> 0.06002265 | D88: =SUMIFS(Trades!$X$2:$X$884,Trades!$Y$2:$Y$884,">=-99",Trades!$Y$2:$Y$884,"<-1.05") -> -5518.95
A89: -1R (full stop) | B89: =COUNTIFS(Trades!$Y$2:$Y$884,">=-1.05",Trades!$Y$2:$Y$884,"<-0.95") -> 334 | C89: =IFERROR(B89/Summary!$C$20,0) -> 0.37825595 | D89: =SUMIFS(Trades!$X$2:$X$884,Trades!$Y$2:$Y$884,">=-1.05",Trades!$Y$2:$Y$884,"<-0.95") -> -40637.85
A90: -0.95R to -0.05R | B90: =COUNTIFS(Trades!$Y$2:$Y$884,">=-0.95",Trades!$Y$2:$Y$884,"<-0.05") -> 28 | C90: =IFERROR(B90/Summary!$C$20,0) -> 0.031710079 | D90: =SUMIFS(Trades!$X$2:$X$884,Trades!$Y$2:$Y$884,">=-0.95",Trades!$Y$2:$Y$884,"<-0.05") -> -195.55
A91: about 0R (breakeven) | B91: =COUNTIFS(Trades!$Y$2:$Y$884,">=-0.05",Trades!$Y$2:$Y$884,"<0.05") -> 186 | C91: =IFERROR(B91/Summary!$C$20,0) -> 0.21064553 | D91: =SUMIFS(Trades!$X$2:$X$884,Trades!$Y$2:$Y$884,">=-0.05",Trades!$Y$2:$Y$884,"<0.05") -> -264.47
A92: 0 to +1R | B92: =COUNTIFS(Trades!$Y$2:$Y$884,">=0.05",Trades!$Y$2:$Y$884,"<1") -> 0 | C92: =IFERROR(B92/Summary!$C$20,0) -> 0 | D92: =SUMIFS(Trades!$X$2:$X$884,Trades!$Y$2:$Y$884,">=0.05",Trades!$Y$2:$Y$884,"<1") -> 0
A93: +1R to +2R | B93: =COUNTIFS(Trades!$Y$2:$Y$884,">=1",Trades!$Y$2:$Y$884,"<2") -> 40 | C93: =IFERROR(B93/Summary!$C$20,0) -> 0.045300113 | D93: =SUMIFS(Trades!$X$2:$X$884,Trades!$Y$2:$Y$884,">=1",Trades!$Y$2:$Y$884,"<2") -> 10803.32
A94: +2R to +3R | B94: =COUNTIFS(Trades!$Y$2:$Y$884,">=2",Trades!$Y$2:$Y$884,"<3") -> 239 | C94: =IFERROR(B94/Summary!$C$20,0) -> 0.27066818 | D94: =SUMIFS(Trades!$X$2:$X$884,Trades!$Y$2:$Y$884,">=2",Trades!$Y$2:$Y$884,"<3") -> 52817.3
A95: +3R and more | B95: =COUNTIFS(Trades!$Y$2:$Y$884,">=3",Trades!$Y$2:$Y$884,"<99") -> 3 | C95: =IFERROR(B95/Summary!$C$20,0) -> 0.0033975085 | D95: =SUMIFS(Trades!$X$2:$X$884,Trades!$Y$2:$Y$884,">=3",Trades!$Y$2:$Y$884,"<99") -> 713.89

Sheet Drawdowns & Streaks
A1: Top 10 drawdown periods (closed trades)
A2: Computed from the trade list when the workbook was built (values, not formulas).
A4: # | B4: Started (peak) | C4: Lowest point | D4: Recovered | E4: Depth $ | F4: Depth % | G4: Trades | H4: Days to recover
A5: 1 | B5: 46100.067 | C5: 46125.821 | D5: 46266.504 | E5: 2246.72 | F5: 0.019223595 | G5: 112 | H5: 166
A6: 2 | B6: 45352.251 | C6: 45595.156 | D6: 45656.651 | E6: 1529.96 | F6: 0.014353841 | G6: 200 | H6: 304
A7: 3 | B7: 45993.709 | C7: 46035.651 | D7: 46055.049 | E7: 1114.46 | F7: 0.0096993275 | G7: 41 | H7: 61
A8: 4 | B8: 45726.74 | C8: 45735.925 | D8: 45747.104 | E8: 1113.69 | F8: 0.010247816 | G8: 14 | H8: 20
A9: 5 | B9: 45022.544 | C9: 45047.266 | D9: 45105.736 | E9: 1108.29 | F9: 0.011058092 | G9: 59 | H9: 83
A10: 6 | B10: 45806.084 | C10: 45819.109 | D10: 45826.075 | E10: 1073.25 | F10: 0.0095772466 | G10: 14 | H10: 19
A11: 7 | B11: 46065.755 | C11: 46084.503 | D11: 46093.09 | E11: 1066.13 | F11: 0.0091531415 | G11: 18 | H11: 27
A12: 8 | B12: 45688.167 | C12: 45700.658 | D12: 45715.709 | E12: 1015.48 | F12: 0.0094126764 | G12: 18 | H12: 27
A13: 9 | B13: 45778.492 | C13: 45784.897 | D13: 45806.084 | E13: 914.5 | F13: 0.0081693289 | G13: 20 | H13: 27
A14: 10 | B14: 45891.724 | C14: 45923.48 | D14: 45940.763 | E14: 759.87 | F14: 0.0067126699 | G14: 35 | H14: 49
A17: Longest streaks
B18: Streak | C18: Trades | D18: Net $ | E18: Started
B19: Winning | C19: 4 | D19: 501.58 | E19: 45296.308
B20: Losing | C20: 13 | D20: -1066.13 | E20: 46066.321
B21: Losing days in a row | C21: 14 | D21: -741.52 | E21: 46003

Sheet MT5 Report
A1: Figures exactly as the MT5 Strategy Tester reported them
A3: History Quality | B3: 100% real ticks
A4: Bars | B4: 1190694
A5: Ticks | B5: 238532808
A6: Symbols | B6: 1
A7: Total Net Profit | B7: 17717.69
A8: Balance Drawdown Absolute | B8: 883.95
A9: Equity Drawdown Absolute | B9: 883.95
A10: Gross Profit | B10: 64334.51
A11: Balance Drawdown Maximal | B11: 2 246.72 (1.92%)
A12: Equity Drawdown Maximal | B12: 2 470.08 (2.11%)
A13: Gross Loss | B13: -46616.82
A14: Balance Drawdown Relative | B14: 1.92% (2 246.72)
A15: Equity Drawdown Relative | B15: 2.11% (2 470.08)
A16: Profit Factor | B16: 1.380071
A17: Expected Payoff | B17: 20.065334
A18: Margin Level | B18: 110.87%
A19: Recovery Factor | B19: 7.172922
A20: Sharpe Ratio | B20: 10.95045
A21: Z-Score | B21: 1.91 (94.39%)
A22: AHPR | B22: 1.0002 (0.02%)
A23: LR Correlation | B23: 0.977318
A24: OnTester result | B24: 0
A25: GHPR | B25: 1.0002 (0.02%)
A26: LR Standard Error | B26: 1131.3498
A27: Correlation (Profits,MFE) | B27: 0.731117
A28: Correlation (Profits,MAE) | B28: 0.407321
A29: Correlation (MFE,MAE) | B29: -0.102358
A30: Minimal position holding time | B30: 0:00:03
A31: Maximal position holding time | B31: 35:42:41
A32: Average position holding time | B32: 0:38:54
A33: Total Trades | B33: 883
A34: Short Trades (won %) | B34: 375 (29.60%)
A35: Long Trades (won %) | B35: 508 (35.24%)
A36: Total Deals | B36: 1766
A37: Profit Trades (% of total) | B37: 290 (32.84%)
A38: Loss Trades (% of total) | B38: 593 (67.16%)
A39: Largest profit trade | B39: 1033.59
A40: Largest loss trade | B40: -568.08
A41: Average profit trade | B41: 221.84314
A42: Average loss trade | B42: -78.611838
A43: Maximum consecutive wins ($) | B43: 4 (1 153.43)
A44: Maximum consecutive losses ($) | B44: 13 (-1 066.13)
A45: Maximal consecutive profit (count) | B45: 1 176.97 (3)
A46: Maximal consecutive loss (count) | B46: -1 525.78 (10)
A47: Average consecutive wins | B47: 1
A48: Average consecutive losses | B48: 3

Sheet Settings
A1: Test settings and EA inputs
A3: Expert | B3: Pdh pdl m1 atr
A4: Symbol | B4: NDX100.m_S0
A5: Period | B5: M1 (2023.04.01 - 2026.10.01)
A6: Company | B6: FundingPips Corp
A7: Currency | B7: USD
A8: Initial Deposit | B8: 100000
A9: Leverage | B9: 1:500
A10: History quality | B10: 100% real ticks
A12: Input | B12: Value
A13: Entry
A14: TradeBuys | B14: true
A15: TradeSells | B15: true
A16: Stop Loss / Take Profit (ATR)
A17: ATR_Timeframe | B17: 1
A18: ATR_Period | B18: 10
A19: ATR_SL_Mult | B19: 2
A20: ATR_TP_Mult | B20: 4
A21: Trade Management
A22: UseBreakeven | B22: true
A23: BreakevenAtR | B23: 1.0
A24: UseTimeExit | B24: false
A25: ExitHour | B25: 22
A26: ExitMinute | B26: 45
A27: Position Size
A28: LotMode | B28: 1
A29: FixedLots | B29: 0.01
A30: RiskPercent | B30: 0.5
A31: MaxMarginUsePct | B31: 90.0
A32: Loss Limits (whole account, all EA instances)
A33: DailyLossPct | B33: 2.5
A34: WeeklyLossPct | B34: 8.5
A35: LossBaseAmount | B35: 0.0
A36: Optional Filters (off by default)
A37: MaxSpreadPoints | B37: 0
A38: UseSession | B38: false
A39: SessionStartHour | B39: 8
A40: SessionEndHour | B40: 17
A41: Execution
A42: MagicNumber | B42: 260514
A43: SlippagePoints | B43: 30
